{
  "date" : "Tue, 04 Nov, 2025 10:04:56 +0000",
  "doco" : "For each file: start is seconds after start activity occurred. Length = milliseconds activity took",
  "files" : [
    {
      "name" : "/fsh-generated/resources/ImplementationGuide-ans.fhir.fr.sas.json",
      "size" : 33380,
      "processes" : [
        {
          "activity" : "load",
          "start" : 49,
          "length" : 43
        },
        {
          "activity" : "checkR4R4B",
          "start" : 52,
          "length" : 19
        },
        {
          "activity" : "generateNarratives",
          "start" : 52,
          "length" : 96
        },
        {
          "activity" : "validate",
          "start" : 82,
          "length" : 5678
        },
        {
          "activity" : "scanForUsageStats",
          "start" : 88,
          "length" : 1
        },
        {
          "activity" : "generate1",
          "start" : 94,
          "length" : 228
        },
        {
          "activity" : "generate2",
          "start" : 107,
          "length" : 297
        },
        {
          "activity" : "generateValidationPack",
          "start" : 144,
          "length" : 7
        },
        {
          "activity" : "scanExamplesForR5",
          "start" : 172,
          "length" : 1
        }
      ]
    },
    {
      "name" : "fsh-generated/resources/Appointment-1.json",
      "size" : 1347,
      "processes" : [
        {
          "activity" : "loadResources",
          "start" : 45,
          "length" : 24
        },
        {
          "activity" : "load-configure",
          "start" : 52,
          "length" : 1
        },
        {
          "activity" : "generateNarratives",
          "start" : 52,
          "length" : 544
        },
        {
          "activity" : "validate",
          "start" : 88,
          "length" : 118
        },
        {
          "activity" : "generate1",
          "start" : 94,
          "length" : 96
        },
        {
          "activity" : "generate2",
          "start" : 107,
          "length" : 65
        }
      ]
    },
    {
      "name" : "fsh-generated/resources/Appointment-2.json",
      "size" : 1350,
      "processes" : [
        {
          "activity" : "loadResources",
          "start" : 45,
          "length" : 26
        },
        {
          "activity" : "generateNarratives",
          "start" : 52,
          "length" : 4
        },
        {
          "activity" : "validate",
          "start" : 88,
          "length" : 98
        },
        {
          "activity" : "generate1",
          "start" : 94,
          "length" : 62
        },
        {
          "activity" : "generate2",
          "start" : 107,
          "length" : 51
        }
      ]
    },
    {
      "name" : "fsh-generated/resources/Bundle-ExampleBundleAgregateurSOS.json",
      "size" : 14110,
      "processes" : [
        {
          "activity" : "loadResources",
          "start" : 45,
          "length" : 30
        },
        {
          "activity" : "load",
          "start" : 47,
          "length" : 29
        },
        {
          "activity" : "load",
          "start" : 48,
          "length" : 1
        },
        {
          "activity" : "checkR4R4B",
          "start" : 52,
          "length" : 2
        },
        {
          "activity" : "generateNarratives",
          "start" : 52,
          "length" : 209
        },
        {
          "activity" : "validate",
          "start" : 88,
          "length" : 589
        },
        {
          "activity" : "generate1",
          "start" : 94,
          "length" : 83
        },
        {
          "activity" : "generate2",
          "start" : 107,
          "length" : 98
        }
      ]
    },
    {
      "name" : "fsh-generated/resources/Bundle-ExampleBundleCPTS1.json",
      "size" : 7738,
      "processes" : [
        {
          "activity" : "loadResources",
          "start" : 45,
          "length" : 29
        },
        {
          "activity" : "load",
          "start" : 47,
          "length" : 23
        },
        {
          "activity" : "checkR4R4B",
          "start" : 52,
          "length" : 1
        },
        {
          "activity" : "generateNarratives",
          "start" : 52,
          "length" : 39
        },
        {
          "activity" : "validate",
          "start" : 89,
          "length" : 3303
        },
        {
          "activity" : "generate1",
          "start" : 94,
          "length" : 67
        },
        {
          "activity" : "generate2",
          "start" : 107,
          "length" : 66
        }
      ]
    },
    {
      "name" : "fsh-generated/resources/Bundle-ExampleBundleCPTS2.json",
      "size" : 9771,
      "processes" : [
        {
          "activity" : "loadResources",
          "start" : 45,
          "length" : 27
        },
        {
          "activity" : "load",
          "start" : 47,
          "length" : 14
        },
        {
          "activity" : "load",
          "start" : 49,
          "length" : 1
        },
        {
          "activity" : "load-configure",
          "start" : 52,
          "length" : 1
        },
        {
          "activity" : "checkR4R4B",
          "start" : 52,
          "length" : 1
        },
        {
          "activity" : "generateNarratives",
          "start" : 53,
          "length" : 10
        },
        {
          "activity" : "validate",
          "start" : 92,
          "length" : 220
        },
        {
          "activity" : "generate1",
          "start" : 94,
          "length" : 73
        },
        {
          "activity" : "generate2",
          "start" : 107,
          "length" : 67
        }
      ]
    },
    {
      "name" : "fsh-generated/resources/Bundle-ExampleBundlePSIndiv.json",
      "size" : 17732,
      "processes" : [
        {
          "activity" : "loadResources",
          "start" : 45,
          "length" : 28
        },
        {
          "activity" : "load",
          "start" : 47,
          "length" : 16
        },
        {
          "activity" : "checkR4R4B",
          "start" : 52,
          "length" : 2
        },
        {
          "activity" : "generateNarratives",
          "start" : 53,
          "length" : 21
        },
        {
          "activity" : "validate",
          "start" : 92,
          "length" : 469
        },
        {
          "activity" : "generate1",
          "start" : 95,
          "length" : 107
        },
        {
          "activity" : "generate2",
          "start" : 107,
          "length" : 102
        }
      ]
    },
    {
      "name" : "fsh-generated/resources/CapabilityStatement-SAS-Consommateur-CPTS.json",
      "size" : 3363,
      "processes" : [
        {
          "activity" : "loadResources",
          "start" : 45,
          "length" : 26
        },
        {
          "activity" : "load",
          "start" : 48,
          "length" : 26
        },
        {
          "activity" : "generateNarratives",
          "start" : 53,
          "length" : 73
        },
        {
          "activity" : "validate",
          "start" : 81,
          "length" : 1423
        },
        {
          "activity" : "generate1",
          "start" : 95,
          "length" : 70
        },
        {
          "activity" : "generate2",
          "start" : 107,
          "length" : 66
        },
        {
          "activity" : "generateValidationPack",
          "start" : 144,
          "length" : 1
        }
      ]
    },
    {
      "name" : "fsh-generated/resources/CapabilityStatement-SAS-Consommateur-SOS.json",
      "size" : 4303,
      "processes" : [
        {
          "activity" : "loadResources",
          "start" : 45,
          "length" : 26
        },
        {
          "activity" : "load",
          "start" : 48,
          "length" : 24
        },
        {
          "activity" : "checkR4R4B",
          "start" : 52,
          "length" : 1
        },
        {
          "activity" : "generateNarratives",
          "start" : 53,
          "length" : 56
        },
        {
          "activity" : "validate",
          "start" : 82,
          "length" : 25
        },
        {
          "activity" : "generate1",
          "start" : 95,
          "length" : 70
        },
        {
          "activity" : "generate2",
          "start" : 108,
          "length" : 48
        },
        {
          "activity" : "generateValidationPack",
          "start" : 144,
          "length" : 1
        }
      ]
    },
    {
      "name" : "fsh-generated/resources/CapabilityStatement-SAS-Consommateur-psindiv.json",
      "size" : 3254,
      "processes" : [
        {
          "activity" : "loadResources",
          "start" : 45,
          "length" : 26
        },
        {
          "activity" : "load",
          "start" : 48,
          "length" : 25
        },
        {
          "activity" : "generateNarratives",
          "start" : 53,
          "length" : 38
        },
        {
          "activity" : "validate",
          "start" : 82,
          "length" : 26
        },
        {
          "activity" : "generate1",
          "start" : 95,
          "length" : 66
        },
        {
          "activity" : "generate2",
          "start" : 108,
          "length" : 46
        },
        {
          "activity" : "generateValidationPack",
          "start" : 144,
          "length" : 1
        }
      ]
    },
    {
      "name" : "fsh-generated/resources/CapabilityStatement-SAS-GestionnaireAgenda-CPTS.json",
      "size" : 3323,
      "processes" : [
        {
          "activity" : "loadResources",
          "start" : 46,
          "length" : 26
        },
        {
          "activity" : "load",
          "start" : 48,
          "length" : 24
        },
        {
          "activity" : "checkR4R4B",
          "start" : 52,
          "length" : 1
        },
        {
          "activity" : "generateNarratives",
          "start" : 53,
          "length" : 31
        },
        {
          "activity" : "validate",
          "start" : 82,
          "length" : 34
        },
        {
          "activity" : "generate1",
          "start" : 95,
          "length" : 67
        },
        {
          "activity" : "generate2",
          "start" : 108,
          "length" : 47
        },
        {
          "activity" : "generateValidationPack",
          "start" : 144,
          "length" : 1
        }
      ]
    },
    {
      "name" : "fsh-generated/resources/CapabilityStatement-SAS-GestionnaireAgenda-PsIndiv.json",
      "size" : 3238,
      "processes" : [
        {
          "activity" : "loadResources",
          "start" : 46,
          "length" : 26
        },
        {
          "activity" : "load",
          "start" : 48,
          "length" : 27
        },
        {
          "activity" : "generateNarratives",
          "start" : 53,
          "length" : 31
        },
        {
          "activity" : "validate",
          "start" : 82,
          "length" : 34
        },
        {
          "activity" : "generate1",
          "start" : 95,
          "length" : 65
        },
        {
          "activity" : "generate2",
          "start" : 108,
          "length" : 45
        },
        {
          "activity" : "generateValidationPack",
          "start" : 144,
          "length" : 1
        }
      ]
    },
    {
      "name" : "fsh-generated/resources/CapabilityStatement-SAS-GestionnaireAgenda-RDVSOS.json",
      "size" : 1944,
      "processes" : [
        {
          "activity" : "loadResources",
          "start" : 46,
          "length" : 26
        },
        {
          "activity" : "load",
          "start" : 48,
          "length" : 24
        },
        {
          "activity" : "load-configure",
          "start" : 52,
          "length" : 1
        },
        {
          "activity" : "generateNarratives",
          "start" : 53,
          "length" : 31
        },
        {
          "activity" : "validate",
          "start" : 82,
          "length" : 27
        },
        {
          "activity" : "scanForUsageStats",
          "start" : 88,
          "length" : 1
        },
        {
          "activity" : "generate1",
          "start" : 95,
          "length" : 60
        },
        {
          "activity" : "generate2",
          "start" : 108,
          "length" : 72
        },
        {
          "activity" : "generateValidationPack",
          "start" : 144,
          "length" : 1
        }
      ]
    },
    {
      "name" : "fsh-generated/resources/CapabilityStatement-SAS-GestionnaireAgenda-RDVpsindiv.json",
      "size" : 1944,
      "processes" : [
        {
          "activity" : "loadResources",
          "start" : 46,
          "length" : 25
        },
        {
          "activity" : "load",
          "start" : 48,
          "length" : 26
        },
        {
          "activity" : "checkR4R4B",
          "start" : 52,
          "length" : 1
        },
        {
          "activity" : "generateNarratives",
          "start" : 53,
          "length" : 29
        },
        {
          "activity" : "validate",
          "start" : 82,
          "length" : 26
        },
        {
          "activity" : "generate1",
          "start" : 95,
          "length" : 62
        },
        {
          "activity" : "generate2",
          "start" : 108,
          "length" : 42
        }
      ]
    },
    {
      "name" : "fsh-generated/resources/CapabilityStatement-SAS-GestionnaireAgenda-SOS.json",
      "size" : 4283,
      "processes" : [
        {
          "activity" : "loadResources",
          "start" : 46,
          "length" : 27
        },
        {
          "activity" : "load",
          "start" : 49,
          "length" : 24
        },
        {
          "activity" : "generateNarratives",
          "start" : 53,
          "length" : 33
        },
        {
          "activity" : "validate",
          "start" : 82,
          "length" : 41
        },
        {
          "activity" : "generate1",
          "start" : 95,
          "length" : 69
        },
        {
          "activity" : "generate2",
          "start" : 108,
          "length" : 44
        },
        {
          "activity" : "generateValidationPack",
          "start" : 144,
          "length" : 2
        }
      ]
    },
    {
      "name" : "fsh-generated/resources/CapabilityStatement-SAS-GestionnaireStructure.json",
      "size" : 1837,
      "processes" : [
        {
          "activity" : "loadResources",
          "start" : 46,
          "length" : 23
        },
        {
          "activity" : "load",
          "start" : 49,
          "length" : 25
        },
        {
          "activity" : "generateNarratives",
          "start" : 53,
          "length" : 31
        },
        {
          "activity" : "validate",
          "start" : 82,
          "length" : 27
        },
        {
          "activity" : "generate1",
          "start" : 95,
          "length" : 64
        },
        {
          "activity" : "generate2",
          "start" : 108,
          "length" : 41
        },
        {
          "activity" : "scanExamplesForR5",
          "start" : 172,
          "length" : 1
        }
      ]
    },
    {
      "name" : "fsh-generated/resources/CodeSystem-categorie-orientation-sas-codesystem.json",
      "size" : 956,
      "processes" : [
        {
          "activity" : "loadResources",
          "start" : 46,
          "length" : 26
        },
        {
          "activity" : "load",
          "start" : 48,
          "length" : 26
        },
        {
          "activity" : "generateNarratives",
          "start" : 53,
          "length" : 28
        },
        {
          "activity" : "validate",
          "start" : 54,
          "length" : 1271
        },
        {
          "activity" : "checkConformanceResources",
          "start" : 88,
          "length" : 1
        },
        {
          "activity" : "generate1",
          "start" : 95,
          "length" : 54
        },
        {
          "activity" : "generate2",
          "start" : 108,
          "length" : 490
        },
        {
          "activity" : "generateValidationPack",
          "start" : 144,
          "length" : 1
        }
      ]
    },
    {
      "name" : "fsh-generated/resources/HealthcareService-ExampleHealthcareServiceCPTS1.json",
      "size" : 304,
      "processes" : [
        {
          "activity" : "loadResources",
          "start" : 46,
          "length" : 26
        },
        {
          "activity" : "generateNarratives",
          "start" : 53,
          "length" : 1
        },
        {
          "activity" : "validate",
          "start" : 93,
          "length" : 6
        },
        {
          "activity" : "generate1",
          "start" : 95,
          "length" : 52
        },
        {
          "activity" : "generate2",
          "start" : 108,
          "length" : 53
        }
      ]
    },
    {
      "name" : "fsh-generated/resources/HealthcareService-ExampleHealthcareServiceCPTS2.json",
      "size" : 304,
      "processes" : [
        {
          "activity" : "loadResources",
          "start" : 46,
          "length" : 26
        },
        {
          "activity" : "validate",
          "start" : 93,
          "length" : 2
        },
        {
          "activity" : "generate1",
          "start" : 95,
          "length" : 51
        },
        {
          "activity" : "generate2",
          "start" : 108,
          "length" : 52
        }
      ]
    },
    {
      "name" : "fsh-generated/resources/Location-1111111111.json",
      "size" : 1071,
      "processes" : [
        {
          "activity" : "loadResources",
          "start" : 46,
          "length" : 27
        },
        {
          "activity" : "checkR4R4B",
          "start" : 52,
          "length" : 1
        },
        {
          "activity" : "generateNarratives",
          "start" : 53,
          "length" : 2
        },
        {
          "activity" : "validate",
          "start" : 93,
          "length" : 24
        },
        {
          "activity" : "generate1",
          "start" : 95,
          "length" : 52
        },
        {
          "activity" : "generate2",
          "start" : 109,
          "length" : 52
        }
      ]
    },
    {
      "name" : "fsh-generated/resources/Location-2222222222.json",
      "size" : 1032,
      "processes" : [
        {
          "activity" : "loadResources",
          "start" : 46,
          "length" : 26
        },
        {
          "activity" : "generateNarratives",
          "start" : 53,
          "length" : 2
        },
        {
          "activity" : "validate",
          "start" : 93,
          "length" : 19
        },
        {
          "activity" : "generate1",
          "start" : 95,
          "length" : 52
        },
        {
          "activity" : "generate2",
          "start" : 109,
          "length" : 52
        }
      ]
    },
    {
      "name" : "fsh-generated/resources/Location-3333333333.json",
      "size" : 1011,
      "processes" : [
        {
          "activity" : "loadResources",
          "start" : 46,
          "length" : 26
        },
        {
          "activity" : "load-configure",
          "start" : 52,
          "length" : 1
        },
        {
          "activity" : "generateNarratives",
          "start" : 53,
          "length" : 1
        },
        {
          "activity" : "validate",
          "start" : 93,
          "length" : 19
        },
        {
          "activity" : "generate1",
          "start" : 95,
          "length" : 52
        },
        {
          "activity" : "generate2",
          "start" : 109,
          "length" : 51
        }
      ]
    },
    {
      "name" : "fsh-generated/resources/Organization-ExampleOrgaCPTS1.json",
      "size" : 624,
      "processes" : [
        {
          "activity" : "loadResources",
          "start" : 46,
          "length" : 26
        },
        {
          "activity" : "generateNarratives",
          "start" : 53,
          "length" : 1
        },
        {
          "activity" : "validate",
          "start" : 93,
          "length" : 14
        },
        {
          "activity" : "generate1",
          "start" : 96,
          "length" : 51
        },
        {
          "activity" : "generate2",
          "start" : 109,
          "length" : 49
        }
      ]
    },
    {
      "name" : "fsh-generated/resources/Organization-ExampleOrgaCPTS2.json",
      "size" : 631,
      "processes" : [
        {
          "activity" : "loadResources",
          "start" : 46,
          "length" : 26
        },
        {
          "activity" : "validate",
          "start" : 93,
          "length" : 18
        },
        {
          "activity" : "generate1",
          "start" : 96,
          "length" : 52
        },
        {
          "activity" : "generate2",
          "start" : 109,
          "length" : 49
        }
      ]
    },
    {
      "name" : "fsh-generated/resources/Organization-ExampleOrgaSOS1.json",
      "size" : 558,
      "processes" : [
        {
          "activity" : "loadResources",
          "start" : 46,
          "length" : 25
        },
        {
          "activity" : "generateNarratives",
          "start" : 53,
          "length" : 1
        },
        {
          "activity" : "validate",
          "start" : 93,
          "length" : 13
        },
        {
          "activity" : "generate1",
          "start" : 96,
          "length" : 51
        },
        {
          "activity" : "generate2",
          "start" : 109,
          "length" : 49
        }
      ]
    },
    {
      "name" : "fsh-generated/resources/Organization-ExampleOrgaSOS2.json",
      "size" : 574,
      "processes" : [
        {
          "activity" : "loadResources",
          "start" : 46,
          "length" : 26
        },
        {
          "activity" : "generateNarratives",
          "start" : 53,
          "length" : 1
        },
        {
          "activity" : "validate",
          "start" : 93,
          "length" : 12
        },
        {
          "activity" : "generate1",
          "start" : 96,
          "length" : 51
        },
        {
          "activity" : "generate2",
          "start" : 109,
          "length" : 49
        }
      ]
    },
    {
      "name" : "fsh-generated/resources/Practitioner-ExamplePractitioner.json",
      "size" : 570,
      "processes" : [
        {
          "activity" : "loadResources",
          "start" : 46,
          "length" : 26
        },
        {
          "activity" : "validate",
          "start" : 93,
          "length" : 16
        },
        {
          "activity" : "generate1",
          "start" : 96,
          "length" : 54
        },
        {
          "activity" : "generate2",
          "start" : 109,
          "length" : 50
        }
      ]
    },
    {
      "name" : "fsh-generated/resources/Practitioner-ExamplePractitioner2.json",
      "size" : 576,
      "processes" : [
        {
          "activity" : "loadResources",
          "start" : 46,
          "length" : 25
        },
        {
          "activity" : "generateNarratives",
          "start" : 53,
          "length" : 1
        },
        {
          "activity" : "validate",
          "start" : 93,
          "length" : 21
        },
        {
          "activity" : "generate1",
          "start" : 96,
          "length" : 51
        },
        {
          "activity" : "generate2",
          "start" : 109,
          "length" : 49
        }
      ]
    },
    {
      "name" : "fsh-generated/resources/Practitioner-ExamplePractitioner3.json",
      "size" : 575,
      "processes" : [
        {
          "activity" : "loadResources",
          "start" : 46,
          "length" : 26
        },
        {
          "activity" : "generateNarratives",
          "start" : 53,
          "length" : 1
        },
        {
          "activity" : "validate",
          "start" : 93,
          "length" : 16
        },
        {
          "activity" : "generate1",
          "start" : 96,
          "length" : 52
        },
        {
          "activity" : "generate2",
          "start" : 109,
          "length" : 48
        }
      ]
    },
    {
      "name" : "fsh-generated/resources/Practitioner-ExamplePractitionerRegul1.json",
      "size" : 770,
      "processes" : [
        {
          "activity" : "loadResources",
          "start" : 46,
          "length" : 25
        },
        {
          "activity" : "generateNarratives",
          "start" : 53,
          "length" : 8
        },
        {
          "activity" : "validate",
          "start" : 93,
          "length" : 40
        },
        {
          "activity" : "generate1",
          "start" : 96,
          "length" : 50
        },
        {
          "activity" : "generate2",
          "start" : 109,
          "length" : 50
        }
      ]
    },
    {
      "name" : "fsh-generated/resources/Practitioner-ExamplePractitionerRegul2.json",
      "size" : 752,
      "processes" : [
        {
          "activity" : "loadResources",
          "start" : 46,
          "length" : 25
        },
        {
          "activity" : "checkR4R4B",
          "start" : 52,
          "length" : 1
        },
        {
          "activity" : "generateNarratives",
          "start" : 53,
          "length" : 11
        },
        {
          "activity" : "validate",
          "start" : 93,
          "length" : 39
        },
        {
          "activity" : "generate1",
          "start" : 96,
          "length" : 51
        },
        {
          "activity" : "generate2",
          "start" : 109,
          "length" : 50
        }
      ]
    },
    {
      "name" : "fsh-generated/resources/Practitioner-ExamplePractitionerRegul3.json",
      "size" : 753,
      "processes" : [
        {
          "activity" : "loadResources",
          "start" : 46,
          "length" : 25
        },
        {
          "activity" : "generateNarratives",
          "start" : 53,
          "length" : 10
        },
        {
          "activity" : "validate",
          "start" : 93,
          "length" : 38
        },
        {
          "activity" : "generate1",
          "start" : 96,
          "length" : 51
        },
        {
          "activity" : "generate2",
          "start" : 109,
          "length" : 49
        }
      ]
    },
    {
      "name" : "fsh-generated/resources/Practitioner-ExamplePractitionerRegul4.json",
      "size" : 786,
      "processes" : [
        {
          "activity" : "loadResources",
          "start" : 46,
          "length" : 26
        },
        {
          "activity" : "generateNarratives",
          "start" : 53,
          "length" : 11
        },
        {
          "activity" : "validate",
          "start" : 93,
          "length" : 43
        },
        {
          "activity" : "generate1",
          "start" : 96,
          "length" : 51
        },
        {
          "activity" : "generate2",
          "start" : 109,
          "length" : 50
        }
      ]
    },
    {
      "name" : "fsh-generated/resources/PractitionerRole-ExamplePractitionerRoleAgregateur.json",
      "size" : 1262,
      "processes" : [
        {
          "activity" : "loadResources",
          "start" : 46,
          "length" : 26
        },
        {
          "activity" : "load-configure",
          "start" : 52,
          "length" : 1
        },
        {
          "activity" : "generateNarratives",
          "start" : 53,
          "length" : 2
        },
        {
          "activity" : "validate",
          "start" : 93,
          "length" : 31
        },
        {
          "activity" : "generate1",
          "start" : 96,
          "length" : 60
        },
        {
          "activity" : "generate2",
          "start" : 109,
          "length" : 53
        }
      ]
    },
    {
      "name" : "fsh-generated/resources/PractitionerRole-ExamplePractitionerRoleAgregateur2.json",
      "size" : 1393,
      "processes" : [
        {
          "activity" : "loadResources",
          "start" : 46,
          "length" : 25
        },
        {
          "activity" : "generateNarratives",
          "start" : 53,
          "length" : 1
        },
        {
          "activity" : "validate",
          "start" : 93,
          "length" : 40
        },
        {
          "activity" : "generate1",
          "start" : 96,
          "length" : 53
        },
        {
          "activity" : "generate2",
          "start" : 109,
          "length" : 54
        }
      ]
    },
    {
      "name" : "fsh-generated/resources/PractitionerRole-ExamplePractitionerRoleAgregateur3.json",
      "size" : 1394,
      "processes" : [
        {
          "activity" : "loadResources",
          "start" : 46,
          "length" : 24
        },
        {
          "activity" : "generateNarratives",
          "start" : 53,
          "length" : 2
        },
        {
          "activity" : "validate",
          "start" : 93,
          "length" : 44
        },
        {
          "activity" : "generate1",
          "start" : 96,
          "length" : 56
        },
        {
          "activity" : "generate2",
          "start" : 109,
          "length" : 53
        }
      ]
    },
    {
      "name" : "fsh-generated/resources/PractitionerRole-ExamplePractitionerRoleAgregateur4.json",
      "size" : 1480,
      "processes" : [
        {
          "activity" : "loadResources",
          "start" : 46,
          "length" : 26
        },
        {
          "activity" : "generateNarratives",
          "start" : 53,
          "length" : 1
        },
        {
          "activity" : "validate",
          "start" : 93,
          "length" : 37
        },
        {
          "activity" : "generate1",
          "start" : 96,
          "length" : 53
        },
        {
          "activity" : "generate2",
          "start" : 109,
          "length" : 55
        }
      ]
    },
    {
      "name" : "fsh-generated/resources/Schedule-ExampleSchedule.json",
      "size" : 337,
      "processes" : [
        {
          "activity" : "loadResources",
          "start" : 46,
          "length" : 25
        },
        {
          "activity" : "generateNarratives",
          "start" : 53,
          "length" : 1
        },
        {
          "activity" : "validate",
          "start" : 93,
          "length" : 1
        },
        {
          "activity" : "generate1",
          "start" : 96,
          "length" : 51
        },
        {
          "activity" : "generate2",
          "start" : 109,
          "length" : 53
        }
      ]
    },
    {
      "name" : "fsh-generated/resources/Schedule-ExampleSchedule1.json",
      "size" : 340,
      "processes" : [
        {
          "activity" : "loadResources",
          "start" : 46,
          "length" : 26
        },
        {
          "activity" : "generateNarratives",
          "start" : 53,
          "length" : 1
        },
        {
          "activity" : "validate",
          "start" : 93,
          "length" : 2
        },
        {
          "activity" : "generate1",
          "start" : 96,
          "length" : 51
        },
        {
          "activity" : "generate2",
          "start" : 109,
          "length" : 54
        }
      ]
    },
    {
      "name" : "fsh-generated/resources/Schedule-ExampleSchedule2.json",
      "size" : 340,
      "processes" : [
        {
          "activity" : "loadResources",
          "start" : 46,
          "length" : 25
        },
        {
          "activity" : "validate",
          "start" : 93,
          "length" : 2
        },
        {
          "activity" : "generate1",
          "start" : 96,
          "length" : 50
        },
        {
          "activity" : "generate2",
          "start" : 110,
          "length" : 52
        }
      ]
    },
    {
      "name" : "fsh-generated/resources/Schedule-ExampleSchedule3.json",
      "size" : 340,
      "processes" : [
        {
          "activity" : "loadResources",
          "start" : 46,
          "length" : 23
        },
        {
          "activity" : "generateNarratives",
          "start" : 53,
          "length" : 1
        },
        {
          "activity" : "validate",
          "start" : 93,
          "length" : 3
        },
        {
          "activity" : "generate1",
          "start" : 96,
          "length" : 51
        },
        {
          "activity" : "generate2",
          "start" : 110,
          "length" : 57
        }
      ]
    },
    {
      "name" : "fsh-generated/resources/Schedule-ExampleScheduleSOS1.json",
      "size" : 274,
      "processes" : [
        {
          "activity" : "loadResources",
          "start" : 46,
          "length" : 25
        },
        {
          "activity" : "generateNarratives",
          "start" : 53,
          "length" : 1
        },
        {
          "activity" : "validate",
          "start" : 93,
          "length" : 1
        },
        {
          "activity" : "generate1",
          "start" : 97,
          "length" : 51
        },
        {
          "activity" : "generate2",
          "start" : 110,
          "length" : 50
        }
      ]
    },
    {
      "name" : "fsh-generated/resources/Schedule-ExampleScheduleSOS2.json",
      "size" : 274,
      "processes" : [
        {
          "activity" : "loadResources",
          "start" : 46,
          "length" : 26
        },
        {
          "activity" : "checkR4R4B",
          "start" : 52,
          "length" : 1
        },
        {
          "activity" : "validate",
          "start" : 93,
          "length" : 2
        },
        {
          "activity" : "generate1",
          "start" : 97,
          "length" : 54
        },
        {
          "activity" : "generate2",
          "start" : 110,
          "length" : 49
        }
      ]
    },
    {
      "name" : "fsh-generated/resources/Schedule-ExampleScheduleSOS3.json",
      "size" : 274,
      "processes" : [
        {
          "activity" : "loadResources",
          "start" : 46,
          "length" : 25
        },
        {
          "activity" : "load-configure",
          "start" : 52,
          "length" : 1
        },
        {
          "activity" : "validate",
          "start" : 93,
          "length" : 1
        },
        {
          "activity" : "generate1",
          "start" : 97,
          "length" : 52
        },
        {
          "activity" : "generate2",
          "start" : 110,
          "length" : 49
        }
      ]
    },
    {
      "name" : "fsh-generated/resources/SearchParameter-cptsslot-sp-servicetype.json",
      "size" : 611,
      "processes" : [
        {
          "activity" : "loadResources",
          "start" : 46,
          "length" : 25
        },
        {
          "activity" : "load",
          "start" : 48,
          "length" : 29
        },
        {
          "activity" : "load",
          "start" : 49,
          "length" : 25
        },
        {
          "activity" : "generateNarratives",
          "start" : 53,
          "length" : 41
        },
        {
          "activity" : "validate",
          "start" : 81,
          "length" : 6
        },
        {
          "activity" : "generate1",
          "start" : 97,
          "length" : 52
        },
        {
          "activity" : "generate2",
          "start" : 110,
          "length" : 39
        }
      ]
    },
    {
      "name" : "fsh-generated/resources/SearchParameter-slot-sp-start.json",
      "size" : 598,
      "processes" : [
        {
          "activity" : "loadResources",
          "start" : 46,
          "length" : 23
        },
        {
          "activity" : "load",
          "start" : 48,
          "length" : 25
        },
        {
          "activity" : "load",
          "start" : 49,
          "length" : 24
        },
        {
          "activity" : "generateNarratives",
          "start" : 53,
          "length" : 29
        },
        {
          "activity" : "validate",
          "start" : 81,
          "length" : 4
        },
        {
          "activity" : "generate1",
          "start" : 97,
          "length" : 55
        },
        {
          "activity" : "generate2",
          "start" : 110,
          "length" : 39
        }
      ]
    },
    {
      "name" : "fsh-generated/resources/Slot-ExampleSlotCPTS1.json",
      "size" : 1779,
      "processes" : [
        {
          "activity" : "loadResources",
          "start" : 46,
          "length" : 23
        },
        {
          "activity" : "generateNarratives",
          "start" : 53,
          "length" : 3
        },
        {
          "activity" : "validate",
          "start" : 93,
          "length" : 61
        },
        {
          "activity" : "generate1",
          "start" : 97,
          "length" : 53
        },
        {
          "activity" : "generate2",
          "start" : 110,
          "length" : 52
        }
      ]
    },
    {
      "name" : "fsh-generated/resources/Slot-ExampleSlotCPTS2.json",
      "size" : 2229,
      "processes" : [
        {
          "activity" : "loadResources",
          "start" : 46,
          "length" : 26
        },
        {
          "activity" : "generateNarratives",
          "start" : 53,
          "length" : 4
        },
        {
          "activity" : "validate",
          "start" : 93,
          "length" : 70
        },
        {
          "activity" : "generate1",
          "start" : 97,
          "length" : 59
        },
        {
          "activity" : "generate2",
          "start" : 110,
          "length" : 52
        }
      ]
    },
    {
      "name" : "fsh-generated/resources/Slot-ExampleSlotPSIndiv1.json",
      "size" : 1501,
      "processes" : [
        {
          "activity" : "loadResources",
          "start" : 46,
          "length" : 25
        },
        {
          "activity" : "generateNarratives",
          "start" : 53,
          "length" : 2
        },
        {
          "activity" : "validate",
          "start" : 93,
          "length" : 38
        },
        {
          "activity" : "generate1",
          "start" : 97,
          "length" : 53
        },
        {
          "activity" : "generate2",
          "start" : 110,
          "length" : 50
        }
      ]
    },
    {
      "name" : "fsh-generated/resources/Slot-ExampleSlotPSIndiv2.json",
      "size" : 1096,
      "processes" : [
        {
          "activity" : "loadResources",
          "start" : 47,
          "length" : 26
        },
        {
          "activity" : "generateNarratives",
          "start" : 53,
          "length" : 2
        },
        {
          "activity" : "validate",
          "start" : 93,
          "length" : 25
        },
        {
          "activity" : "generate1",
          "start" : 97,
          "length" : 54
        },
        {
          "activity" : "generate2",
          "start" : 110,
          "length" : 51
        }
      ]
    },
    {
      "name" : "fsh-generated/resources/Slot-ExampleSlotPSIndiv3.json",
      "size" : 1350,
      "processes" : [
        {
          "activity" : "loadResources",
          "start" : 47,
          "length" : 25
        },
        {
          "activity" : "checkR4R4B",
          "start" : 52,
          "length" : 1
        },
        {
          "activity" : "generateNarratives",
          "start" : 53,
          "length" : 3
        },
        {
          "activity" : "validate",
          "start" : 94,
          "length" : 31
        },
        {
          "activity" : "generate1",
          "start" : 97,
          "length" : 53
        },
        {
          "activity" : "generate2",
          "start" : 110,
          "length" : 51
        }
      ]
    },
    {
      "name" : "fsh-generated/resources/Slot-ExampleSlotPSIndiv4.json",
      "size" : 1549,
      "processes" : [
        {
          "activity" : "loadResources",
          "start" : 47,
          "length" : 26
        },
        {
          "activity" : "generateNarratives",
          "start" : 53,
          "length" : 2
        },
        {
          "activity" : "validate",
          "start" : 94,
          "length" : 31
        },
        {
          "activity" : "generate1",
          "start" : 97,
          "length" : 54
        },
        {
          "activity" : "generate2",
          "start" : 110,
          "length" : 51
        }
      ]
    },
    {
      "name" : "fsh-generated/resources/Slot-ExampleSlotSOS1.json",
      "size" : 1219,
      "processes" : [
        {
          "activity" : "loadResources",
          "start" : 47,
          "length" : 33
        },
        {
          "activity" : "generateNarratives",
          "start" : 53,
          "length" : 3
        },
        {
          "activity" : "validate",
          "start" : 94,
          "length" : 27
        },
        {
          "activity" : "generate1",
          "start" : 97,
          "length" : 54
        },
        {
          "activity" : "generate2",
          "start" : 110,
          "length" : 53
        }
      ]
    },
    {
      "name" : "fsh-generated/resources/Slot-ExampleSlotSOS2.json",
      "size" : 927,
      "processes" : [
        {
          "activity" : "loadResources",
          "start" : 47,
          "length" : 26
        },
        {
          "activity" : "generateNarratives",
          "start" : 53,
          "length" : 1
        },
        {
          "activity" : "validate",
          "start" : 94,
          "length" : 18
        },
        {
          "activity" : "generate1",
          "start" : 97,
          "length" : 52
        },
        {
          "activity" : "generate2",
          "start" : 110,
          "length" : 53
        }
      ]
    },
    {
      "name" : "fsh-generated/resources/Slot-ExampleSlotSOS3.json",
      "size" : 926,
      "processes" : [
        {
          "activity" : "loadResources",
          "start" : 47,
          "length" : 24
        },
        {
          "activity" : "load-configure",
          "start" : 52,
          "length" : 1
        },
        {
          "activity" : "generateNarratives",
          "start" : 53,
          "length" : 2
        },
        {
          "activity" : "validate",
          "start" : 94,
          "length" : 17
        },
        {
          "activity" : "generate1",
          "start" : 97,
          "length" : 52
        },
        {
          "activity" : "generate2",
          "start" : 110,
          "length" : 52
        }
      ]
    },
    {
      "name" : "fsh-generated/resources/Slot-ExampleSlotSOS4.json",
      "size" : 927,
      "processes" : [
        {
          "activity" : "loadResources",
          "start" : 47,
          "length" : 26
        },
        {
          "activity" : "generateNarratives",
          "start" : 53,
          "length" : 2
        },
        {
          "activity" : "validate",
          "start" : 94,
          "length" : 18
        },
        {
          "activity" : "generate1",
          "start" : 97,
          "length" : 52
        },
        {
          "activity" : "generate2",
          "start" : 110,
          "length" : 51
        }
      ]
    },
    {
      "name" : "fsh-generated/resources/StructureDefinition-BundleAgregateur.json",
      "size" : 3082,
      "processes" : [
        {
          "activity" : "loadResources",
          "start" : 47,
          "length" : 26
        },
        {
          "activity" : "load",
          "start" : 48,
          "length" : 35
        },
        {
          "activity" : "generateSnapshots",
          "start" : 49,
          "length" : 506
        },
        {
          "activity" : "checkR4R4B",
          "start" : 52,
          "length" : 1
        },
        {
          "activity" : "generateNarratives",
          "start" : 53,
          "length" : 105
        },
        {
          "activity" : "validate",
          "start" : 56,
          "length" : 2600
        },
        {
          "activity" : "scanForUsageStats",
          "start" : 88,
          "length" : 2
        },
        {
          "activity" : "generate1",
          "start" : 97,
          "length" : 382
        },
        {
          "activity" : "generate2",
          "start" : 110,
          "length" : 2063
        },
        {
          "activity" : "generate2",
          "start" : 120,
          "length" : 1276
        },
        {
          "activity" : "generateValidationPack",
          "start" : 144,
          "length" : 14
        },
        {
          "activity" : "scanExamplesForR5",
          "start" : 172,
          "length" : 1
        }
      ]
    },
    {
      "name" : "fsh-generated/resources/StructureDefinition-FrAppointmentSAS.json",
      "size" : 5246,
      "processes" : [
        {
          "activity" : "loadResources",
          "start" : 47,
          "length" : 34
        },
        {
          "activity" : "load",
          "start" : 48,
          "length" : 29
        },
        {
          "activity" : "generateSnapshots",
          "start" : 49,
          "length" : 127
        },
        {
          "activity" : "generateNarratives",
          "start" : 53,
          "length" : 77
        },
        {
          "activity" : "validate",
          "start" : 59,
          "length" : 1344
        },
        {
          "activity" : "scanForUsageStats",
          "start" : 88,
          "length" : 1
        },
        {
          "activity" : "generate1",
          "start" : 98,
          "length" : 367
        },
        {
          "activity" : "generate2",
          "start" : 112,
          "length" : 523
        },
        {
          "activity" : "generate2",
          "start" : 121,
          "length" : 540
        },
        {
          "activity" : "generateValidationPack",
          "start" : 144,
          "length" : 13
        },
        {
          "activity" : "scanExamplesForR5",
          "start" : 172,
          "length" : 1
        }
      ]
    },
    {
      "name" : "fsh-generated/resources/StructureDefinition-FrLocationAgregateur.json",
      "size" : 1491,
      "processes" : [
        {
          "activity" : "loadResources",
          "start" : 47,
          "length" : 27
        },
        {
          "activity" : "load",
          "start" : 48,
          "length" : 24
        },
        {
          "activity" : "generateSnapshots",
          "start" : 49,
          "length" : 83
        },
        {
          "activity" : "generateNarratives",
          "start" : 53,
          "length" : 49
        },
        {
          "activity" : "validate",
          "start" : 60,
          "length" : 819
        },
        {
          "activity" : "generate1",
          "start" : 98,
          "length" : 195
        },
        {
          "activity" : "generate2",
          "start" : 113,
          "length" : 310
        },
        {
          "activity" : "generate2",
          "start" : 121,
          "length" : 291
        },
        {
          "activity" : "generateValidationPack",
          "start" : 144,
          "length" : 6
        },
        {
          "activity" : "scanProfilesForR5",
          "start" : 172,
          "length" : 1
        }
      ]
    },
    {
      "name" : "fsh-generated/resources/StructureDefinition-FrPractitionerAgregateur.json",
      "size" : 1817,
      "processes" : [
        {
          "activity" : "loadResources",
          "start" : 47,
          "length" : 26
        },
        {
          "activity" : "load",
          "start" : 48,
          "length" : 24
        },
        {
          "activity" : "generateSnapshots",
          "start" : 49,
          "length" : 74
        },
        {
          "activity" : "generateNarratives",
          "start" : 53,
          "length" : 79
        },
        {
          "activity" : "validate",
          "start" : 61,
          "length" : 2736
        },
        {
          "activity" : "checkConformanceResources",
          "start" : 88,
          "length" : 1
        },
        {
          "activity" : "scanForUsageStats",
          "start" : 88,
          "length" : 2
        },
        {
          "activity" : "generate1",
          "start" : 98,
          "length" : 435
        },
        {
          "activity" : "generate2",
          "start" : 113,
          "length" : 629
        },
        {
          "activity" : "generate2",
          "start" : 122,
          "length" : 565
        },
        {
          "activity" : "generateValidationPack",
          "start" : 144,
          "length" : 15
        },
        {
          "activity" : "scanExamplesForR5",
          "start" : 172,
          "length" : 2
        }
      ]
    },
    {
      "name" : "fsh-generated/resources/StructureDefinition-FrPractitionerRegul.json",
      "size" : 3078,
      "processes" : [
        {
          "activity" : "loadResources",
          "start" : 47,
          "length" : 26
        },
        {
          "activity" : "load",
          "start" : 48,
          "length" : 24
        },
        {
          "activity" : "generateSnapshots",
          "start" : 49,
          "length" : 157
        },
        {
          "activity" : "generateNarratives",
          "start" : 53,
          "length" : 129
        },
        {
          "activity" : "validate",
          "start" : 64,
          "length" : 3127
        },
        {
          "activity" : "scanForUsageStats",
          "start" : 88,
          "length" : 2
        },
        {
          "activity" : "generate1",
          "start" : 99,
          "length" : 530
        },
        {
          "activity" : "generate2",
          "start" : 114,
          "length" : 1107
        },
        {
          "activity" : "generate2",
          "start" : 122,
          "length" : 550
        },
        {
          "activity" : "generateValidationPack",
          "start" : 144,
          "length" : 17
        },
        {
          "activity" : "scanExamplesForR5",
          "start" : 172,
          "length" : 2
        }
      ]
    },
    {
      "name" : "fsh-generated/resources/StructureDefinition-FrPractitionerRoleExerciceAgregateur.json",
      "size" : 2533,
      "processes" : [
        {
          "activity" : "loadResources",
          "start" : 47,
          "length" : 26
        },
        {
          "activity" : "load",
          "start" : 48,
          "length" : 25
        },
        {
          "activity" : "generateSnapshots",
          "start" : 50,
          "length" : 33
        },
        {
          "activity" : "generateNarratives",
          "start" : 54,
          "length" : 44
        },
        {
          "activity" : "validate",
          "start" : 67,
          "length" : 643
        },
        {
          "activity" : "scanForUsageStats",
          "start" : 88,
          "length" : 1
        },
        {
          "activity" : "generate1",
          "start" : 99,
          "length" : 200
        },
        {
          "activity" : "generate2",
          "start" : 115,
          "length" : 393
        },
        {
          "activity" : "generate2",
          "start" : 123,
          "length" : 150
        },
        {
          "activity" : "generateValidationPack",
          "start" : 144,
          "length" : 6
        }
      ]
    },
    {
      "name" : "fsh-generated/resources/StructureDefinition-FrScheduleAgregateur.json",
      "size" : 1469,
      "processes" : [
        {
          "activity" : "loadResources",
          "start" : 47,
          "length" : 25
        },
        {
          "activity" : "load",
          "start" : 48,
          "length" : 29
        },
        {
          "activity" : "generateSnapshots",
          "start" : 50,
          "length" : 31
        },
        {
          "activity" : "load-configure",
          "start" : 52,
          "length" : 1
        },
        {
          "activity" : "generateNarratives",
          "start" : 54,
          "length" : 33
        },
        {
          "activity" : "validate",
          "start" : 67,
          "length" : 368
        },
        {
          "activity" : "generate1",
          "start" : 99,
          "length" : 116
        },
        {
          "activity" : "generate2",
          "start" : 115,
          "length" : 216
        },
        {
          "activity" : "generate2",
          "start" : 123,
          "length" : 90
        },
        {
          "activity" : "generateValidationPack",
          "start" : 144,
          "length" : 3
        }
      ]
    },
    {
      "name" : "fsh-generated/resources/StructureDefinition-FrSlotAgregateur.json",
      "size" : 4381,
      "processes" : [
        {
          "activity" : "loadResources",
          "start" : 47,
          "length" : 26
        },
        {
          "activity" : "load",
          "start" : 48,
          "length" : 26
        },
        {
          "activity" : "generateSnapshots",
          "start" : 50,
          "length" : 34
        },
        {
          "activity" : "generateNarratives",
          "start" : 54,
          "length" : 44
        },
        {
          "activity" : "validate",
          "start" : 68,
          "length" : 538
        },
        {
          "activity" : "scanForUsageStats",
          "start" : 88,
          "length" : 1
        },
        {
          "activity" : "generate1",
          "start" : 100,
          "length" : 177
        },
        {
          "activity" : "generate2",
          "start" : 116,
          "length" : 250
        },
        {
          "activity" : "generate2",
          "start" : 123,
          "length" : 117
        },
        {
          "activity" : "generateValidationPack",
          "start" : 144,
          "length" : 6
        },
        {
          "activity" : "scanExamplesForR5",
          "start" : 172,
          "length" : 1
        }
      ]
    },
    {
      "name" : "fsh-generated/resources/StructureDefinition-sas-categorie-orientation.json",
      "size" : 1500,
      "processes" : [
        {
          "activity" : "loadResources",
          "start" : 47,
          "length" : 25
        },
        {
          "activity" : "load",
          "start" : 48,
          "length" : 23
        },
        {
          "activity" : "generateSnapshots",
          "start" : 50,
          "length" : 27
        },
        {
          "activity" : "generateNarratives",
          "start" : 54,
          "length" : 30
        },
        {
          "activity" : "validate",
          "start" : 68,
          "length" : 2334
        },
        {
          "activity" : "generate1",
          "start" : 100,
          "length" : 72
        },
        {
          "activity" : "generate2",
          "start" : 116,
          "length" : 69
        },
        {
          "activity" : "generate2",
          "start" : 123,
          "length" : 26
        },
        {
          "activity" : "generateValidationPack",
          "start" : 144,
          "length" : 1
        }
      ]
    },
    {
      "name" : "fsh-generated/resources/StructureDefinition-sas-cpts-bundle-aggregator.json",
      "size" : 5247,
      "processes" : [
        {
          "activity" : "loadResources",
          "start" : 47,
          "length" : 26
        },
        {
          "activity" : "load",
          "start" : 48,
          "length" : 26
        },
        {
          "activity" : "generateSnapshots",
          "start" : 50,
          "length" : 253
        },
        {
          "activity" : "generateNarratives",
          "start" : 54,
          "length" : 66
        },
        {
          "activity" : "validate",
          "start" : 71,
          "length" : 2189
        },
        {
          "activity" : "scanForUsageStats",
          "start" : 88,
          "length" : 2
        },
        {
          "activity" : "generate1",
          "start" : 100,
          "length" : 487
        },
        {
          "activity" : "generate2",
          "start" : 116,
          "length" : 868
        },
        {
          "activity" : "generate2",
          "start" : 123,
          "length" : 401
        },
        {
          "activity" : "generateValidationPack",
          "start" : 144,
          "length" : 17
        },
        {
          "activity" : "scanExamplesForR5",
          "start" : 172,
          "length" : 1
        }
      ]
    },
    {
      "name" : "fsh-generated/resources/StructureDefinition-sas-cpts-healthcareservice-aggregator.json",
      "size" : 1216,
      "processes" : [
        {
          "activity" : "loadResources",
          "start" : 47,
          "length" : 26
        },
        {
          "activity" : "load",
          "start" : 48,
          "length" : 24
        },
        {
          "activity" : "generateSnapshots",
          "start" : 50,
          "length" : 34
        },
        {
          "activity" : "generateNarratives",
          "start" : 54,
          "length" : 36
        },
        {
          "activity" : "validate",
          "start" : 73,
          "length" : 642
        },
        {
          "activity" : "checkConformanceResources",
          "start" : 88,
          "length" : 1
        },
        {
          "activity" : "generate1",
          "start" : 100,
          "length" : 167
        },
        {
          "activity" : "generate2",
          "start" : 117,
          "length" : 208
        },
        {
          "activity" : "generate2",
          "start" : 124,
          "length" : 128
        },
        {
          "activity" : "generateValidationPack",
          "start" : 144,
          "length" : 5
        }
      ]
    },
    {
      "name" : "fsh-generated/resources/StructureDefinition-sas-cpts-organization-aggregator.json",
      "size" : 1936,
      "processes" : [
        {
          "activity" : "loadResources",
          "start" : 47,
          "length" : 25
        },
        {
          "activity" : "load",
          "start" : 48,
          "length" : 25
        },
        {
          "activity" : "generateSnapshots",
          "start" : 50,
          "length" : 40
        },
        {
          "activity" : "generateNarratives",
          "start" : 54,
          "length" : 43
        },
        {
          "activity" : "validate",
          "start" : 73,
          "length" : 1156
        },
        {
          "activity" : "scanForUsageStats",
          "start" : 88,
          "length" : 1
        },
        {
          "activity" : "generate1",
          "start" : 100,
          "length" : 236
        },
        {
          "activity" : "generate2",
          "start" : 117,
          "length" : 301
        },
        {
          "activity" : "generate2",
          "start" : 124,
          "length" : 152
        },
        {
          "activity" : "generateValidationPack",
          "start" : 144,
          "length" : 8
        },
        {
          "activity" : "scanProfilesForR5",
          "start" : 172,
          "length" : 1
        },
        {
          "activity" : "scanExamplesForR5",
          "start" : 172,
          "length" : 1
        }
      ]
    },
    {
      "name" : "fsh-generated/resources/StructureDefinition-sas-cpts-slot-aggregator.json",
      "size" : 4598,
      "processes" : [
        {
          "activity" : "loadResources",
          "start" : 47,
          "length" : 26
        },
        {
          "activity" : "load",
          "start" : 48,
          "length" : 36
        },
        {
          "activity" : "generateSnapshots",
          "start" : 50,
          "length" : 35
        },
        {
          "activity" : "load-configure",
          "start" : 52,
          "length" : 1
        },
        {
          "activity" : "generateNarratives",
          "start" : 54,
          "length" : 48
        },
        {
          "activity" : "validate",
          "start" : 75,
          "length" : 771
        },
        {
          "activity" : "scanForUsageStats",
          "start" : 88,
          "length" : 1
        },
        {
          "activity" : "generate1",
          "start" : 101,
          "length" : 222
        },
        {
          "activity" : "generate2",
          "start" : 117,
          "length" : 215
        },
        {
          "activity" : "generate2",
          "start" : 124,
          "length" : 75
        },
        {
          "activity" : "generateValidationPack",
          "start" : 144,
          "length" : 7
        },
        {
          "activity" : "scanExamplesForR5",
          "start" : 172,
          "length" : 1
        }
      ]
    },
    {
      "name" : "fsh-generated/resources/StructureDefinition-sas-cpts-slot-servicetype-aggregator.json",
      "size" : 1669,
      "processes" : [
        {
          "activity" : "loadResources",
          "start" : 47,
          "length" : 25
        },
        {
          "activity" : "load",
          "start" : 48,
          "length" : 25
        },
        {
          "activity" : "generateSnapshots",
          "start" : 50,
          "length" : 26
        },
        {
          "activity" : "generateNarratives",
          "start" : 54,
          "length" : 29
        },
        {
          "activity" : "validate",
          "start" : 75,
          "length" : 80
        },
        {
          "activity" : "generate1",
          "start" : 101,
          "length" : 71
        },
        {
          "activity" : "generate2",
          "start" : 118,
          "length" : 66
        },
        {
          "activity" : "generate2",
          "start" : 124,
          "length" : 15
        },
        {
          "activity" : "generateValidationPack",
          "start" : 144,
          "length" : 1
        }
      ]
    },
    {
      "name" : "fsh-generated/resources/StructureDefinition-sas-sos-appointment.json",
      "size" : 4193,
      "processes" : [
        {
          "activity" : "loadResources",
          "start" : 47,
          "length" : 26
        },
        {
          "activity" : "load",
          "start" : 48,
          "length" : 25
        },
        {
          "activity" : "generateSnapshots",
          "start" : 50,
          "length" : 120
        },
        {
          "activity" : "generateNarratives",
          "start" : 54,
          "length" : 49
        },
        {
          "activity" : "validate",
          "start" : 75,
          "length" : 906
        },
        {
          "activity" : "scanForUsageStats",
          "start" : 88,
          "length" : 1
        },
        {
          "activity" : "generate1",
          "start" : 101,
          "length" : 257
        },
        {
          "activity" : "generate2",
          "start" : 118,
          "length" : 262
        },
        {
          "activity" : "generate2",
          "start" : 124,
          "length" : 97
        },
        {
          "activity" : "generateValidationPack",
          "start" : 144,
          "length" : 8
        }
      ]
    },
    {
      "name" : "fsh-generated/resources/StructureDefinition-sas-sos-bundle-aggregator.json",
      "size" : 3965,
      "processes" : [
        {
          "activity" : "loadResources",
          "start" : 47,
          "length" : 25
        },
        {
          "activity" : "load",
          "start" : 48,
          "length" : 25
        },
        {
          "activity" : "generateSnapshots",
          "start" : 50,
          "length" : 225
        },
        {
          "activity" : "generateNarratives",
          "start" : 54,
          "length" : 57
        },
        {
          "activity" : "validate",
          "start" : 76,
          "length" : 1505
        },
        {
          "activity" : "scanForUsageStats",
          "start" : 88,
          "length" : 1
        },
        {
          "activity" : "generate1",
          "start" : 101,
          "length" : 373
        },
        {
          "activity" : "generate2",
          "start" : 118,
          "length" : 517
        },
        {
          "activity" : "generate2",
          "start" : 124,
          "length" : 203
        },
        {
          "activity" : "generateValidationPack",
          "start" : 144,
          "length" : 13
        },
        {
          "activity" : "scanExamplesForR5",
          "start" : 172,
          "length" : 1
        }
      ]
    },
    {
      "name" : "fsh-generated/resources/StructureDefinition-sas-sos-location-aggregator.json",
      "size" : 2114,
      "processes" : [
        {
          "activity" : "loadResources",
          "start" : 47,
          "length" : 26
        },
        {
          "activity" : "load",
          "start" : 48,
          "length" : 26
        },
        {
          "activity" : "generateSnapshots",
          "start" : 50,
          "length" : 36
        },
        {
          "activity" : "generateNarratives",
          "start" : 54,
          "length" : 46
        },
        {
          "activity" : "validate",
          "start" : 78,
          "length" : 815
        },
        {
          "activity" : "scanForUsageStats",
          "start" : 88,
          "length" : 1
        },
        {
          "activity" : "generate1",
          "start" : 102,
          "length" : 217
        },
        {
          "activity" : "generate2",
          "start" : 118,
          "length" : 240
        },
        {
          "activity" : "generate2",
          "start" : 124,
          "length" : 109
        },
        {
          "activity" : "makeDependencies",
          "start" : 129,
          "length" : 1
        },
        {
          "activity" : "generateValidationPack",
          "start" : 144,
          "length" : 8
        },
        {
          "activity" : "scanExamplesForR5",
          "start" : 172,
          "length" : 1
        }
      ]
    },
    {
      "name" : "fsh-generated/resources/StructureDefinition-sas-sos-organization-aggregator.json",
      "size" : 1743,
      "processes" : [
        {
          "activity" : "loadResources",
          "start" : 47,
          "length" : 23
        },
        {
          "activity" : "load",
          "start" : 48,
          "length" : 27
        },
        {
          "activity" : "generateSnapshots",
          "start" : 51,
          "length" : 37
        },
        {
          "activity" : "generateNarratives",
          "start" : 54,
          "length" : 42
        },
        {
          "activity" : "validate",
          "start" : 79,
          "length" : 1108
        },
        {
          "activity" : "scanForUsageStats",
          "start" : 88,
          "length" : 1
        },
        {
          "activity" : "generate1",
          "start" : 102,
          "length" : 231
        },
        {
          "activity" : "generate2",
          "start" : 119,
          "length" : 279
        },
        {
          "activity" : "generate2",
          "start" : 124,
          "length" : 110
        },
        {
          "activity" : "generateValidationPack",
          "start" : 144,
          "length" : 7
        },
        {
          "activity" : "scanExamplesForR5",
          "start" : 172,
          "length" : 1
        }
      ]
    },
    {
      "name" : "fsh-generated/resources/StructureDefinition-sas-sos-schedule-aggregator.json",
      "size" : 1065,
      "processes" : [
        {
          "activity" : "loadResources",
          "start" : 47,
          "length" : 23
        },
        {
          "activity" : "load",
          "start" : 48,
          "length" : 24
        },
        {
          "activity" : "generateSnapshots",
          "start" : 51,
          "length" : 30
        },
        {
          "activity" : "generateNarratives",
          "start" : 54,
          "length" : 32
        },
        {
          "activity" : "validate",
          "start" : 80,
          "length" : 403
        },
        {
          "activity" : "generate1",
          "start" : 102,
          "length" : 128
        },
        {
          "activity" : "generate2",
          "start" : 119,
          "length" : 126
        },
        {
          "activity" : "generate2",
          "start" : 125,
          "length" : 49
        },
        {
          "activity" : "generateValidationPack",
          "start" : 144,
          "length" : 4
        }
      ]
    },
    {
      "name" : "fsh-generated/resources/StructureDefinition-sas-sos-slot-aggregator.json",
      "size" : 1926,
      "processes" : [
        {
          "activity" : "loadResources",
          "start" : 47,
          "length" : 22
        },
        {
          "activity" : "load",
          "start" : 48,
          "length" : 24
        },
        {
          "activity" : "generateSnapshots",
          "start" : 51,
          "length" : 31
        },
        {
          "activity" : "generateNarratives",
          "start" : 54,
          "length" : 35
        },
        {
          "activity" : "validate",
          "start" : 80,
          "length" : 473
        },
        {
          "activity" : "scanForUsageStats",
          "start" : 88,
          "length" : 1
        },
        {
          "activity" : "generate1",
          "start" : 102,
          "length" : 154
        },
        {
          "activity" : "generate2",
          "start" : 119,
          "length" : 146
        },
        {
          "activity" : "generate2",
          "start" : 125,
          "length" : 51
        },
        {
          "activity" : "generateValidationPack",
          "start" : 144,
          "length" : 4
        }
      ]
    },
    {
      "name" : "fsh-generated/resources/ValueSet-categorie-orientation-sas-valueset.json",
      "size" : 1066,
      "processes" : [
        {
          "activity" : "loadResources",
          "start" : 47,
          "length" : 25
        },
        {
          "activity" : "load",
          "start" : 48,
          "length" : 25
        },
        {
          "activity" : "scan",
          "start" : 52,
          "length" : 1
        },
        {
          "activity" : "checkR4R4B",
          "start" : 52,
          "length" : 1
        },
        {
          "activity" : "generateNarratives",
          "start" : 54,
          "length" : 69
        },
        {
          "activity" : "validate",
          "start" : 56,
          "length" : 69
        },
        {
          "activity" : "generate1",
          "start" : 102,
          "length" : 55
        },
        {
          "activity" : "generate2",
          "start" : 119,
          "length" : 79
        },
        {
          "activity" : "generateValidationPack",
          "start" : 144,
          "length" : 1
        }
      ]
    },
    {
      "name" : "fsh-generated/resources/ValueSet-sas-cpts-valueset-typecreneau.json",
      "size" : 1041,
      "processes" : [
        {
          "activity" : "loadResources",
          "start" : 47,
          "length" : 25
        },
        {
          "activity" : "load",
          "start" : 48,
          "length" : 28
        },
        {
          "activity" : "load-configure",
          "start" : 52,
          "length" : 1
        },
        {
          "activity" : "generateNarratives",
          "start" : 54,
          "length" : 30
        },
        {
          "activity" : "validate",
          "start" : 56,
          "length" : 18
        },
        {
          "activity" : "generate1",
          "start" : 102,
          "length" : 55
        },
        {
          "activity" : "generate2",
          "start" : 119,
          "length" : 62
        }
      ]
    },
    {
      "name" : "fsh-generated/resources/ValueSet-sas-sos-valueset-participant-status.json",
      "size" : 779,
      "processes" : [
        {
          "activity" : "loadResources",
          "start" : 47,
          "length" : 23
        },
        {
          "activity" : "load",
          "start" : 48,
          "length" : 23
        },
        {
          "activity" : "generateNarratives",
          "start" : 54,
          "length" : 27
        },
        {
          "activity" : "validate",
          "start" : 56,
          "length" : 17
        },
        {
          "activity" : "generate1",
          "start" : 102,
          "length" : 52
        },
        {
          "activity" : "generate2",
          "start" : 119,
          "length" : 42
        }
      ]
    },
    {
      "name" : "fsh-generated/resources/ValueSet-sas-sos-valueset-typecreneau.json",
      "size" : 795,
      "processes" : [
        {
          "activity" : "loadResources",
          "start" : 47,
          "length" : 23
        },
        {
          "activity" : "load",
          "start" : 48,
          "length" : 25
        },
        {
          "activity" : "generateNarratives",
          "start" : 54,
          "length" : 27
        },
        {
          "activity" : "validate",
          "start" : 56,
          "length" : 18
        },
        {
          "activity" : "generate1",
          "start" : 103,
          "length" : 53
        },
        {
          "activity" : "generate2",
          "start" : 119,
          "length" : 47
        },
        {
          "activity" : "generateValidationPack",
          "start" : 144,
          "length" : 1
        }
      ]
    },
    {
      "name" : "fsh-generated/resources/ValueSet-sas-valueset-appointmentparticipanttype.json",
      "size" : 706,
      "processes" : [
        {
          "activity" : "loadResources",
          "start" : 47,
          "length" : 25
        },
        {
          "activity" : "load",
          "start" : 48,
          "length" : 26
        },
        {
          "activity" : "generateNarratives",
          "start" : 54,
          "length" : 34
        },
        {
          "activity" : "validate",
          "start" : 56,
          "length" : 26
        },
        {
          "activity" : "generate1",
          "start" : 103,
          "length" : 52
        },
        {
          "activity" : "generate2",
          "start" : 119,
          "length" : 38
        }
      ]
    },
    {
      "name" : "fsh-generated/resources/ValueSet-sas-valueset-appointmentreason.json",
      "size" : 732,
      "processes" : [
        {
          "activity" : "loadResources",
          "start" : 47,
          "length" : 22
        },
        {
          "activity" : "load",
          "start" : 48,
          "length" : 25
        },
        {
          "activity" : "generateNarratives",
          "start" : 54,
          "length" : 27
        },
        {
          "activity" : "validate",
          "start" : 56,
          "length" : 62
        },
        {
          "activity" : "generate1",
          "start" : 103,
          "length" : 52
        },
        {
          "activity" : "generate2",
          "start" : 119,
          "length" : 39
        }
      ]
    },
    {
      "name" : "fsh-generated/resources/ValueSet-sas-valueset-categorieetablissement.json",
      "size" : 705,
      "processes" : [
        {
          "activity" : "loadResources",
          "start" : 47,
          "length" : 26
        },
        {
          "activity" : "load",
          "start" : 48,
          "length" : 24
        },
        {
          "activity" : "checkR4R4B",
          "start" : 52,
          "length" : 1
        },
        {
          "activity" : "generateNarratives",
          "start" : 54,
          "length" : 27
        },
        {
          "activity" : "validate",
          "start" : 56,
          "length" : 16
        },
        {
          "activity" : "generate1",
          "start" : 103,
          "length" : 54
        },
        {
          "activity" : "generate2",
          "start" : 119,
          "length" : 39
        }
      ]
    },
    {
      "name" : "fsh-generated/resources/ValueSet-sas-valueset-typeconsultation.json",
      "size" : 786,
      "processes" : [
        {
          "activity" : "loadResources",
          "start" : 47,
          "length" : 23
        },
        {
          "activity" : "load",
          "start" : 48,
          "length" : 23
        },
        {
          "activity" : "generateNarratives",
          "start" : 54,
          "length" : 26
        },
        {
          "activity" : "validate",
          "start" : 56,
          "length" : 95
        },
        {
          "activity" : "generate1",
          "start" : 103,
          "length" : 53
        },
        {
          "activity" : "generate2",
          "start" : 120,
          "length" : 42
        },
        {
          "activity" : "generateValidationPack",
          "start" : 144,
          "length" : 1
        }
      ]
    },
    {
      "name" : "fsh-generated/resources/ValueSet-sas-valueset-typeidentifiant.json",
      "size" : 710,
      "processes" : [
        {
          "activity" : "loadResources",
          "start" : 47,
          "length" : 25
        },
        {
          "activity" : "load",
          "start" : 48,
          "length" : 24
        },
        {
          "activity" : "generateNarratives",
          "start" : 54,
          "length" : 29
        },
        {
          "activity" : "validate",
          "start" : 56,
          "length" : 16
        },
        {
          "activity" : "generate1",
          "start" : 103,
          "length" : 73
        },
        {
          "activity" : "generate2",
          "start" : 120,
          "length" : 36
        }
      ]
    },
    {
      "name" : "/fsh-generated/includes/fsh-link-references.md",
      "size" : 5645,
      "processes" : [
        {
          "activity" : "generate2",
          "start" : 120,
          "length" : 1
        }
      ]
    },
    {
      "name" : "/fsh-generated/includes/menu.xml",
      "size" : 3944
    },
    {
      "name" : "/input/data/features.yml",
      "size" : 178
    },
    {
      "name" : "/input/pagecontent/specifications_techniques-cpts-gestion_rdv.md",
      "size" : 11100
    },
    {
      "name" : "/input/pagecontent/specifications_techniques.md",
      "size" : 0
    },
    {
      "name" : "/input/pagecontent/specifications_techniques-ps-gestion_rdv.md",
      "size" : 11100,
      "processes" : [
        {
          "activity" : "generate2",
          "start" : 120,
          "length" : 1
        }
      ]
    },
    {
      "name" : "/input/pagecontent/specifications_techniques-tous-gestion_regulateur.md",
      "size" : 8420
    },
    {
      "name" : "/input/pagecontent/specifications_techniques-sos-gestion_regulateur.md",
      "size" : 8420
    },
    {
      "name" : "/input/pagecontent/specifications_techniques.txt",
      "size" : 587,
      "processes" : [
        {
          "activity" : "generate2",
          "start" : 120,
          "length" : 36
        }
      ]
    },
    {
      "name" : "/input/pagecontent/specifications_techniques-tous-gestion_rdv.md",
      "size" : 11100,
      "processes" : [
        {
          "activity" : "generate2",
          "start" : 120,
          "length" : 1
        }
      ]
    },
    {
      "name" : "/input/pagecontent/specifications_techniques-cpts-gestion_regulateur.md",
      "size" : 8420
    },
    {
      "name" : "/input/pagecontent/specifications_techniques-transmission-info-RDV-LRM.md",
      "size" : 45831,
      "processes" : [
        {
          "activity" : "generate2",
          "start" : 120,
          "length" : 1
        }
      ]
    },
    {
      "name" : "/input/pagecontent/specifications_fonctionnelles.md",
      "size" : 22986
    },
    {
      "name" : "/input/pagecontent/securite.md",
      "size" : 2262
    },
    {
      "name" : "/input/pagecontent/ressources_casusage.md",
      "size" : 1957,
      "processes" : [
        {
          "activity" : "generate2",
          "start" : 120,
          "length" : 14
        }
      ]
    },
    {
      "name" : "/input/pagecontent/faq.md",
      "size" : 25185
    },
    {
      "name" : "/input/pagecontent/specifications_techniques-sos-gestion_rdv.md",
      "size" : 11100
    },
    {
      "name" : "/input/pagecontent/annexes.md",
      "size" : 2431,
      "processes" : [
        {
          "activity" : "generate2",
          "start" : 120,
          "length" : 1
        }
      ]
    },
    {
      "name" : "/input/pagecontent/specifications_techniques-ps-recherche_creneaux.md",
      "size" : 14220
    },
    {
      "name" : "/input/pagecontent/specifications_techniques-ps-gestion_regulateur.md",
      "size" : 8420
    },
    {
      "name" : "/input/pagecontent/specifications_techniques-sos-recherche_creneaux.md",
      "size" : 17153
    },
    {
      "name" : "/input/pagecontent/acronymes.md",
      "size" : 1504
    },
    {
      "name" : "/input/pagecontent/downloads.md",
      "size" : 968
    },
    {
      "name" : "/input/pagecontent/specifications_techniques-cpts-recherche_creneaux.md",
      "size" : 15707,
      "processes" : [
        {
          "activity" : "generate2",
          "start" : 120,
          "length" : 1
        }
      ]
    },
    {
      "name" : "/input/pagecontent/index.md",
      "size" : 5259
    },
    {
      "name" : "/input/pagecontent/autres_ressources.md",
      "size" : 0
    },
    {
      "name" : "/template/config",
      "size" : 0
    },
    {
      "name" : "/template/config/_config.yml",
      "size" : 140
    },
    {
      "name" : "/input/images",
      "size" : 0
    },
    {
      "name" : "/input/images/validateur_creneaux-SOS_1.png",
      "size" : 41943
    },
    {
      "name" : "/input/images/validateur_rendez_vous_1.png",
      "size" : 38959,
      "processes" : [
        {
          "activity" : "generate2",
          "start" : 120,
          "length" : 1
        }
      ]
    },
    {
      "name" : "/input/images/recherche_creneaux_2.png",
      "size" : 135856
    },
    {
      "name" : "/input/images/recherche_creneaux_1.png",
      "size" : 121139
    },
    {
      "name" : "/input/images/anImage.png",
      "size" : 36288
    },
    {
      "name" : "/input/images/validateur_creneaux-PS_1.png",
      "size" : 235493
    },
    {
      "name" : "/input/images/schema_mtls.jpg",
      "size" : 25899
    },
    {
      "name" : "/input/images/redescente_rdv_lrm.png",
      "size" : 110368,
      "processes" : [
        {
          "activity" : "generate2",
          "start" : 120,
          "length" : 1
        }
      ]
    },
    {
      "name" : "/input/images/SchemaGlobalRedescenteLRM.png",
      "size" : 69754
    },
    {
      "name" : "/input/images/validateur_rendez_vous_2.png",
      "size" : 40120
    },
    {
      "name" : "/input/images/mecanisme_transmission_regulateurs.png",
      "size" : 62878
    },
    {
      "name" : "/input/images/sas_logo.png",
      "size" : 113157
    },
    {
      "name" : "/input/images/validateur_creneaux-CPTS_2.png",
      "size" : 76542
    },
    {
      "name" : "/input/images/validateur_creneaux-CPTS_1.png",
      "size" : 341806
    },
    {
      "name" : "/input/images/validateur_creneaux-PS_2.png",
      "size" : 76542,
      "processes" : [
        {
          "activity" : "generate2",
          "start" : 120,
          "length" : 1
        }
      ]
    },
    {
      "name" : "/input/images/schema_cas_usage.png",
      "size" : 118501
    },
    {
      "name" : "/input/images/logo_sas.png",
      "size" : 39358,
      "processes" : [
        {
          "activity" : "scan",
          "start" : 52,
          "length" : 1
        }
      ]
    },
    {
      "name" : "/input/images/creation_rendez_vous_1.png",
      "size" : 24681
    },
    {
      "name" : "/temp/pages/_includes/artifacts.xml",
      "size" : 37551
    }
  ]
}
