{
  "resourceType" : "ValueSet",
  "id" : "ed291e5b-3b48-4378-929a-5871b1b82dac-78",
  "url" : "http://hl7.org/fhir/comparison/ValueSet/ed291e5b-3b48-4378-929a-5871b1b82dac-78",
  "name" : "IntersectionAppointmentReasonSASAndAppointmentReasonSAS",
  "title" : "Intersection of Appointment reason SAS And Appointment reason SAS",
  "status" : "active",
  "date" : "2024-12-06T08:28:03+00:00",
  "jurisdiction" : [{
    "coding" : [{
      "system" : "urn:iso:std:iso:3166",
      "code" : "FR",
      "display" : "FRANCE"
    }]
  }],
  "compose" : {
    "include" : [{
      "concept" : [{
        "code" : "ROUTINE",
        "display" : "Créneau avec prise de RDV possible"
      },
      {
        "code" : "WALKIN",
        "display" : "Créneau sans prise de RDV possible à domicile"
      }]
    }]
  }
}