{
  "resourceType" : "ValueSet",
  "id" : "0aa3f12f-480b-42b3-ab9f-0925ad52cc55-81",
  "url" : "http://hl7.org/fhir/comparison/ValueSet/0aa3f12f-480b-42b3-ab9f-0925ad52cc55-81",
  "name" : "IntersectionCategorieEtablissementSASAndCategorieEtablissementSAS",
  "title" : "Intersection of Catégorie établissement SAS And Catégorie établissement SAS",
  "status" : "active",
  "date" : "2024-12-10T09:50:06+00:00",
  "jurisdiction" : [{
    "coding" : [{
      "system" : "urn:iso:std:iso:3166",
      "code" : "FR",
      "display" : "FRANCE"
    }]
  }],
  "compose" : {
    "include" : [{
      "concept" : [{
        "code" : "604",
        "display" : "CPTS"
      }]
    }]
  }
}