{
  "date" : "Tue, 28 Oct, 2025 16:18:27 +0000",
  "doco" : "For each file: start is seconds after start activity occurred. Length = milliseconds activity took",
  "files" : [
    {
      "name" : "/fsh-generated/resources/ImplementationGuide-ans.fhir.fr.sas.json",
      "size" : 33380,
      "processes" : [
        {
          "activity" : "load",
          "start" : 38,
          "length" : 22
        },
        {
          "activity" : "checkR4R4B",
          "start" : 41,
          "length" : 14
        },
        {
          "activity" : "generateNarratives",
          "start" : 41,
          "length" : 54
        },
        {
          "activity" : "validate",
          "start" : 57,
          "length" : 3104
        },
        {
          "activity" : "generate1",
          "start" : 65,
          "length" : 143
        },
        {
          "activity" : "generate2",
          "start" : 73,
          "length" : 168
        },
        {
          "activity" : "generateValidationPack",
          "start" : 110,
          "length" : 8
        },
        {
          "activity" : "scanExamplesForR5",
          "start" : 138,
          "length" : 2
        }
      ]
    },
    {
      "name" : "fsh-generated/resources/Appointment-1.json",
      "size" : 1347,
      "processes" : [
        {
          "activity" : "loadResources",
          "start" : 37,
          "length" : 7
        },
        {
          "activity" : "load-configure",
          "start" : 41,
          "length" : 1
        },
        {
          "activity" : "generateNarratives",
          "start" : 41,
          "length" : 523
        },
        {
          "activity" : "validate",
          "start" : 60,
          "length" : 66
        },
        {
          "activity" : "generate1",
          "start" : 65,
          "length" : 13
        },
        {
          "activity" : "generate2",
          "start" : 73,
          "length" : 25
        }
      ]
    },
    {
      "name" : "fsh-generated/resources/Appointment-2.json",
      "size" : 1350,
      "processes" : [
        {
          "activity" : "loadResources",
          "start" : 37,
          "length" : 5
        },
        {
          "activity" : "checkR4R4B",
          "start" : 41,
          "length" : 1
        },
        {
          "activity" : "generateNarratives",
          "start" : 41,
          "length" : 4
        },
        {
          "activity" : "validate",
          "start" : 60,
          "length" : 45
        },
        {
          "activity" : "generate1",
          "start" : 65,
          "length" : 11
        },
        {
          "activity" : "generate2",
          "start" : 73,
          "length" : 11
        }
      ]
    },
    {
      "name" : "fsh-generated/resources/Bundle-ExampleBundleAgregateurSOS.json",
      "size" : 14110,
      "processes" : [
        {
          "activity" : "loadResources",
          "start" : 37,
          "length" : 10
        },
        {
          "activity" : "load",
          "start" : 38,
          "length" : 19
        },
        {
          "activity" : "load",
          "start" : 38,
          "length" : 1
        },
        {
          "activity" : "checkR4R4B",
          "start" : 41,
          "length" : 1
        },
        {
          "activity" : "generateNarratives",
          "start" : 41,
          "length" : 222
        },
        {
          "activity" : "validate",
          "start" : 61,
          "length" : 311
        },
        {
          "activity" : "generate1",
          "start" : 65,
          "length" : 48
        },
        {
          "activity" : "generate2",
          "start" : 73,
          "length" : 71
        }
      ]
    },
    {
      "name" : "fsh-generated/resources/Bundle-ExampleBundleCPTS1.json",
      "size" : 7738,
      "processes" : [
        {
          "activity" : "loadResources",
          "start" : 37,
          "length" : 8
        },
        {
          "activity" : "load",
          "start" : 38,
          "length" : 13
        },
        {
          "activity" : "checkR4R4B",
          "start" : 41,
          "length" : 1
        },
        {
          "activity" : "generateNarratives",
          "start" : 41,
          "length" : 34
        },
        {
          "activity" : "scanForUsageStats",
          "start" : 60,
          "length" : 1
        },
        {
          "activity" : "validate",
          "start" : 61,
          "length" : 2685
        },
        {
          "activity" : "generate1",
          "start" : 65,
          "length" : 30
        },
        {
          "activity" : "generate2",
          "start" : 73,
          "length" : 42
        }
      ]
    },
    {
      "name" : "fsh-generated/resources/Bundle-ExampleBundleCPTS2.json",
      "size" : 9771,
      "processes" : [
        {
          "activity" : "loadResources",
          "start" : 37,
          "length" : 7
        },
        {
          "activity" : "load",
          "start" : 38,
          "length" : 7
        },
        {
          "activity" : "checkR4R4B",
          "start" : 41,
          "length" : 1
        },
        {
          "activity" : "generateNarratives",
          "start" : 42,
          "length" : 10
        },
        {
          "activity" : "validate",
          "start" : 64,
          "length" : 140
        },
        {
          "activity" : "generate1",
          "start" : 65,
          "length" : 26
        },
        {
          "activity" : "generate2",
          "start" : 73,
          "length" : 42
        }
      ]
    },
    {
      "name" : "fsh-generated/resources/Bundle-ExampleBundlePSIndiv.json",
      "size" : 17732,
      "processes" : [
        {
          "activity" : "loadResources",
          "start" : 37,
          "length" : 10
        },
        {
          "activity" : "load",
          "start" : 38,
          "length" : 6
        },
        {
          "activity" : "load",
          "start" : 38,
          "length" : 1
        },
        {
          "activity" : "checkR4R4B",
          "start" : 41,
          "length" : 2
        },
        {
          "activity" : "generateNarratives",
          "start" : 42,
          "length" : 23
        },
        {
          "activity" : "validate",
          "start" : 64,
          "length" : 241
        },
        {
          "activity" : "generate1",
          "start" : 65,
          "length" : 45
        },
        {
          "activity" : "generate2",
          "start" : 73,
          "length" : 73
        }
      ]
    },
    {
      "name" : "fsh-generated/resources/CapabilityStatement-SAS-Consommateur-CPTS.json",
      "size" : 3363,
      "processes" : [
        {
          "activity" : "loadResources",
          "start" : 37,
          "length" : 5
        },
        {
          "activity" : "load",
          "start" : 38,
          "length" : 7
        },
        {
          "activity" : "load-configure",
          "start" : 41,
          "length" : 1
        },
        {
          "activity" : "generateNarratives",
          "start" : 42,
          "length" : 45
        },
        {
          "activity" : "validate",
          "start" : 55,
          "length" : 1867
        },
        {
          "activity" : "generate1",
          "start" : 65,
          "length" : 41
        },
        {
          "activity" : "generate2",
          "start" : 73,
          "length" : 76
        },
        {
          "activity" : "generateValidationPack",
          "start" : 110,
          "length" : 1
        }
      ]
    },
    {
      "name" : "fsh-generated/resources/CapabilityStatement-SAS-Consommateur-SOS.json",
      "size" : 4303,
      "processes" : [
        {
          "activity" : "loadResources",
          "start" : 37,
          "length" : 5
        },
        {
          "activity" : "load",
          "start" : 38,
          "length" : 6
        },
        {
          "activity" : "generateNarratives",
          "start" : 42,
          "length" : 22
        },
        {
          "activity" : "validate",
          "start" : 57,
          "length" : 17
        },
        {
          "activity" : "generate1",
          "start" : 65,
          "length" : 30
        },
        {
          "activity" : "generate2",
          "start" : 73,
          "length" : 20
        },
        {
          "activity" : "generateValidationPack",
          "start" : 110,
          "length" : 2
        }
      ]
    },
    {
      "name" : "fsh-generated/resources/CapabilityStatement-SAS-Consommateur-psindiv.json",
      "size" : 3254,
      "processes" : [
        {
          "activity" : "loadResources",
          "start" : 37,
          "length" : 5
        },
        {
          "activity" : "load",
          "start" : 38,
          "length" : 6
        },
        {
          "activity" : "checkR4R4B",
          "start" : 41,
          "length" : 1
        },
        {
          "activity" : "generateNarratives",
          "start" : 42,
          "length" : 20
        },
        {
          "activity" : "validate",
          "start" : 57,
          "length" : 16
        },
        {
          "activity" : "generate1",
          "start" : 65,
          "length" : 34
        },
        {
          "activity" : "generate2",
          "start" : 73,
          "length" : 17
        },
        {
          "activity" : "generateValidationPack",
          "start" : 110,
          "length" : 1
        }
      ]
    },
    {
      "name" : "fsh-generated/resources/CapabilityStatement-SAS-GestionnaireAgenda-CPTS.json",
      "size" : 3323,
      "processes" : [
        {
          "activity" : "loadResources",
          "start" : 37,
          "length" : 5
        },
        {
          "activity" : "load",
          "start" : 38,
          "length" : 7
        },
        {
          "activity" : "generateNarratives",
          "start" : 42,
          "length" : 20
        },
        {
          "activity" : "validate",
          "start" : 57,
          "length" : 15
        },
        {
          "activity" : "generate1",
          "start" : 65,
          "length" : 81
        },
        {
          "activity" : "generate2",
          "start" : 73,
          "length" : 19
        },
        {
          "activity" : "generateValidationPack",
          "start" : 110,
          "length" : 1
        }
      ]
    },
    {
      "name" : "fsh-generated/resources/CapabilityStatement-SAS-GestionnaireAgenda-PsIndiv.json",
      "size" : 3238,
      "processes" : [
        {
          "activity" : "loadResources",
          "start" : 37,
          "length" : 4
        },
        {
          "activity" : "load",
          "start" : 38,
          "length" : 5
        },
        {
          "activity" : "generateNarratives",
          "start" : 42,
          "length" : 18
        },
        {
          "activity" : "validate",
          "start" : 57,
          "length" : 13
        },
        {
          "activity" : "generate1",
          "start" : 65,
          "length" : 50
        },
        {
          "activity" : "generate2",
          "start" : 74,
          "length" : 22
        },
        {
          "activity" : "generateValidationPack",
          "start" : 110,
          "length" : 1
        }
      ]
    },
    {
      "name" : "fsh-generated/resources/CapabilityStatement-SAS-GestionnaireAgenda-RDVSOS.json",
      "size" : 1944,
      "processes" : [
        {
          "activity" : "loadResources",
          "start" : 37,
          "length" : 5
        },
        {
          "activity" : "load",
          "start" : 38,
          "length" : 5
        },
        {
          "activity" : "checkR4R4B",
          "start" : 41,
          "length" : 1
        },
        {
          "activity" : "generateNarratives",
          "start" : 42,
          "length" : 16
        },
        {
          "activity" : "validate",
          "start" : 57,
          "length" : 9
        },
        {
          "activity" : "generate1",
          "start" : 65,
          "length" : 93
        },
        {
          "activity" : "generate2",
          "start" : 74,
          "length" : 23
        },
        {
          "activity" : "generateValidationPack",
          "start" : 110,
          "length" : 1
        }
      ]
    },
    {
      "name" : "fsh-generated/resources/CapabilityStatement-SAS-GestionnaireAgenda-RDVpsindiv.json",
      "size" : 1944,
      "processes" : [
        {
          "activity" : "loadResources",
          "start" : 37,
          "length" : 4
        },
        {
          "activity" : "load",
          "start" : 38,
          "length" : 7
        },
        {
          "activity" : "generateNarratives",
          "start" : 42,
          "length" : 16
        },
        {
          "activity" : "validate",
          "start" : 57,
          "length" : 10
        },
        {
          "activity" : "generate1",
          "start" : 65,
          "length" : 18
        },
        {
          "activity" : "generate2",
          "start" : 74,
          "length" : 21
        },
        {
          "activity" : "generateValidationPack",
          "start" : 110,
          "length" : 1
        }
      ]
    },
    {
      "name" : "fsh-generated/resources/CapabilityStatement-SAS-GestionnaireAgenda-SOS.json",
      "size" : 4283,
      "processes" : [
        {
          "activity" : "loadResources",
          "start" : 37,
          "length" : 5
        },
        {
          "activity" : "load",
          "start" : 38,
          "length" : 5
        },
        {
          "activity" : "load-configure",
          "start" : 41,
          "length" : 1
        },
        {
          "activity" : "generateNarratives",
          "start" : 42,
          "length" : 19
        },
        {
          "activity" : "validate",
          "start" : 57,
          "length" : 15
        },
        {
          "activity" : "validate",
          "start" : 60,
          "length" : 1
        },
        {
          "activity" : "generate1",
          "start" : 65,
          "length" : 32
        },
        {
          "activity" : "generate2",
          "start" : 74,
          "length" : 25
        },
        {
          "activity" : "generateValidationPack",
          "start" : 110,
          "length" : 1
        }
      ]
    },
    {
      "name" : "fsh-generated/resources/CapabilityStatement-SAS-GestionnaireStructure.json",
      "size" : 1837,
      "processes" : [
        {
          "activity" : "loadResources",
          "start" : 37,
          "length" : 4
        },
        {
          "activity" : "load",
          "start" : 38,
          "length" : 5
        },
        {
          "activity" : "checkR4R4B",
          "start" : 41,
          "length" : 1
        },
        {
          "activity" : "generateNarratives",
          "start" : 42,
          "length" : 15
        },
        {
          "activity" : "validate",
          "start" : 57,
          "length" : 10
        },
        {
          "activity" : "generate1",
          "start" : 65,
          "length" : 17
        },
        {
          "activity" : "generate2",
          "start" : 74,
          "length" : 20
        },
        {
          "activity" : "generateValidationPack",
          "start" : 110,
          "length" : 1
        }
      ]
    },
    {
      "name" : "fsh-generated/resources/CodeSystem-categorie-orientation-sas-codesystem.json",
      "size" : 956,
      "processes" : [
        {
          "activity" : "loadResources",
          "start" : 37,
          "length" : 6
        },
        {
          "activity" : "load",
          "start" : 38,
          "length" : 9
        },
        {
          "activity" : "generateNarratives",
          "start" : 42,
          "length" : 13
        },
        {
          "activity" : "validate",
          "start" : 43,
          "length" : 1060
        },
        {
          "activity" : "generate1",
          "start" : 65,
          "length" : 13
        },
        {
          "activity" : "generate2",
          "start" : 74,
          "length" : 561
        }
      ]
    },
    {
      "name" : "fsh-generated/resources/HealthcareService-ExampleHealthcareServiceCPTS1.json",
      "size" : 304,
      "processes" : [
        {
          "activity" : "loadResources",
          "start" : 37,
          "length" : 4
        },
        {
          "activity" : "generateNarratives",
          "start" : 42,
          "length" : 1
        },
        {
          "activity" : "validate",
          "start" : 64,
          "length" : 8
        },
        {
          "activity" : "generate1",
          "start" : 65,
          "length" : 9
        },
        {
          "activity" : "generate2",
          "start" : 74,
          "length" : 25
        }
      ]
    },
    {
      "name" : "fsh-generated/resources/HealthcareService-ExampleHealthcareServiceCPTS2.json",
      "size" : 304,
      "processes" : [
        {
          "activity" : "loadResources",
          "start" : 37,
          "length" : 5
        },
        {
          "activity" : "generateNarratives",
          "start" : 42,
          "length" : 1
        },
        {
          "activity" : "validate",
          "start" : 64,
          "length" : 4
        },
        {
          "activity" : "generate1",
          "start" : 65,
          "length" : 10
        },
        {
          "activity" : "generate2",
          "start" : 74,
          "length" : 12
        }
      ]
    },
    {
      "name" : "fsh-generated/resources/Location-1111111111.json",
      "size" : 1071,
      "processes" : [
        {
          "activity" : "loadResources",
          "start" : 37,
          "length" : 4
        },
        {
          "activity" : "generateNarratives",
          "start" : 42,
          "length" : 2
        },
        {
          "activity" : "validate",
          "start" : 64,
          "length" : 16
        },
        {
          "activity" : "generate1",
          "start" : 65,
          "length" : 10
        },
        {
          "activity" : "generate2",
          "start" : 74,
          "length" : 12
        }
      ]
    },
    {
      "name" : "fsh-generated/resources/Location-2222222222.json",
      "size" : 1032,
      "processes" : [
        {
          "activity" : "loadResources",
          "start" : 37,
          "length" : 5
        },
        {
          "activity" : "generateNarratives",
          "start" : 42,
          "length" : 1
        },
        {
          "activity" : "validate",
          "start" : 64,
          "length" : 12
        },
        {
          "activity" : "generate1",
          "start" : 65,
          "length" : 12
        },
        {
          "activity" : "generate2",
          "start" : 74,
          "length" : 16
        }
      ]
    },
    {
      "name" : "fsh-generated/resources/Location-3333333333.json",
      "size" : 1011,
      "processes" : [
        {
          "activity" : "loadResources",
          "start" : 37,
          "length" : 4
        },
        {
          "activity" : "generateNarratives",
          "start" : 42,
          "length" : 2
        },
        {
          "activity" : "validate",
          "start" : 64,
          "length" : 13
        },
        {
          "activity" : "generate1",
          "start" : 65,
          "length" : 11
        },
        {
          "activity" : "generate2",
          "start" : 74,
          "length" : 17
        }
      ]
    },
    {
      "name" : "fsh-generated/resources/Organization-ExampleOrgaCPTS1.json",
      "size" : 624,
      "processes" : [
        {
          "activity" : "loadResources",
          "start" : 37,
          "length" : 4
        },
        {
          "activity" : "validate",
          "start" : 64,
          "length" : 7
        },
        {
          "activity" : "generate1",
          "start" : 65,
          "length" : 13
        },
        {
          "activity" : "generate2",
          "start" : 74,
          "length" : 15
        }
      ]
    },
    {
      "name" : "fsh-generated/resources/Organization-ExampleOrgaCPTS2.json",
      "size" : 631,
      "processes" : [
        {
          "activity" : "loadResources",
          "start" : 37,
          "length" : 4
        },
        {
          "activity" : "generateNarratives",
          "start" : 42,
          "length" : 1
        },
        {
          "activity" : "validate",
          "start" : 64,
          "length" : 8
        },
        {
          "activity" : "generate1",
          "start" : 65,
          "length" : 10
        },
        {
          "activity" : "generate2",
          "start" : 74,
          "length" : 11
        }
      ]
    },
    {
      "name" : "fsh-generated/resources/Organization-ExampleOrgaSOS1.json",
      "size" : 558,
      "processes" : [
        {
          "activity" : "loadResources",
          "start" : 37,
          "length" : 4
        },
        {
          "activity" : "load-configure",
          "start" : 41,
          "length" : 1
        },
        {
          "activity" : "generateNarratives",
          "start" : 42,
          "length" : 1
        },
        {
          "activity" : "validate",
          "start" : 64,
          "length" : 9
        },
        {
          "activity" : "generate1",
          "start" : 65,
          "length" : 9
        },
        {
          "activity" : "generate2",
          "start" : 74,
          "length" : 9
        }
      ]
    },
    {
      "name" : "fsh-generated/resources/Organization-ExampleOrgaSOS2.json",
      "size" : 574,
      "processes" : [
        {
          "activity" : "loadResources",
          "start" : 37,
          "length" : 4
        },
        {
          "activity" : "validate",
          "start" : 64,
          "length" : 8
        },
        {
          "activity" : "generate1",
          "start" : 65,
          "length" : 10
        },
        {
          "activity" : "generate2",
          "start" : 74,
          "length" : 10
        }
      ]
    },
    {
      "name" : "fsh-generated/resources/Practitioner-ExamplePractitioner.json",
      "size" : 570,
      "processes" : [
        {
          "activity" : "loadResources",
          "start" : 37,
          "length" : 6
        },
        {
          "activity" : "checkR4R4B",
          "start" : 41,
          "length" : 1
        },
        {
          "activity" : "generateNarratives",
          "start" : 42,
          "length" : 1
        },
        {
          "activity" : "validate",
          "start" : 64,
          "length" : 9
        },
        {
          "activity" : "generate1",
          "start" : 65,
          "length" : 9
        },
        {
          "activity" : "generate2",
          "start" : 74,
          "length" : 13
        }
      ]
    },
    {
      "name" : "fsh-generated/resources/Practitioner-ExamplePractitioner2.json",
      "size" : 576,
      "processes" : [
        {
          "activity" : "loadResources",
          "start" : 37,
          "length" : 5
        },
        {
          "activity" : "generateNarratives",
          "start" : 42,
          "length" : 1
        },
        {
          "activity" : "validate",
          "start" : 64,
          "length" : 9
        },
        {
          "activity" : "generate1",
          "start" : 65,
          "length" : 9
        },
        {
          "activity" : "generate2",
          "start" : 74,
          "length" : 9
        }
      ]
    },
    {
      "name" : "fsh-generated/resources/Practitioner-ExamplePractitioner3.json",
      "size" : 575,
      "processes" : [
        {
          "activity" : "loadResources",
          "start" : 37,
          "length" : 5
        },
        {
          "activity" : "validate",
          "start" : 64,
          "length" : 10
        },
        {
          "activity" : "generate1",
          "start" : 65,
          "length" : 10
        },
        {
          "activity" : "generate2",
          "start" : 74,
          "length" : 8
        }
      ]
    },
    {
      "name" : "fsh-generated/resources/Practitioner-ExamplePractitionerRegul1.json",
      "size" : 770,
      "processes" : [
        {
          "activity" : "loadResources",
          "start" : 37,
          "length" : 4
        },
        {
          "activity" : "generateNarratives",
          "start" : 42,
          "length" : 4
        },
        {
          "activity" : "validate",
          "start" : 64,
          "length" : 22
        },
        {
          "activity" : "generate1",
          "start" : 65,
          "length" : 10
        },
        {
          "activity" : "generate2",
          "start" : 74,
          "length" : 9
        }
      ]
    },
    {
      "name" : "fsh-generated/resources/Practitioner-ExamplePractitionerRegul2.json",
      "size" : 752,
      "processes" : [
        {
          "activity" : "loadResources",
          "start" : 37,
          "length" : 4
        },
        {
          "activity" : "generateNarratives",
          "start" : 42,
          "length" : 4
        },
        {
          "activity" : "validate",
          "start" : 64,
          "length" : 21
        },
        {
          "activity" : "generate1",
          "start" : 65,
          "length" : 10
        },
        {
          "activity" : "generate2",
          "start" : 74,
          "length" : 9
        }
      ]
    },
    {
      "name" : "fsh-generated/resources/Practitioner-ExamplePractitionerRegul3.json",
      "size" : 753,
      "processes" : [
        {
          "activity" : "loadResources",
          "start" : 37,
          "length" : 5
        },
        {
          "activity" : "generateNarratives",
          "start" : 42,
          "length" : 4
        },
        {
          "activity" : "validate",
          "start" : 64,
          "length" : 23
        },
        {
          "activity" : "generate1",
          "start" : 65,
          "length" : 10
        },
        {
          "activity" : "generate2",
          "start" : 74,
          "length" : 9
        }
      ]
    },
    {
      "name" : "fsh-generated/resources/Practitioner-ExamplePractitionerRegul4.json",
      "size" : 786,
      "processes" : [
        {
          "activity" : "loadResources",
          "start" : 37,
          "length" : 4
        },
        {
          "activity" : "generateNarratives",
          "start" : 42,
          "length" : 4
        },
        {
          "activity" : "validate",
          "start" : 64,
          "length" : 28
        },
        {
          "activity" : "generate1",
          "start" : 65,
          "length" : 11
        },
        {
          "activity" : "generate2",
          "start" : 74,
          "length" : 9
        }
      ]
    },
    {
      "name" : "fsh-generated/resources/PractitionerRole-ExamplePractitionerRoleAgregateur.json",
      "size" : 1262,
      "processes" : [
        {
          "activity" : "loadResources",
          "start" : 37,
          "length" : 4
        },
        {
          "activity" : "generateNarratives",
          "start" : 42,
          "length" : 2
        },
        {
          "activity" : "validate",
          "start" : 64,
          "length" : 17
        },
        {
          "activity" : "generate1",
          "start" : 65,
          "length" : 19
        },
        {
          "activity" : "generate2",
          "start" : 74,
          "length" : 13
        }
      ]
    },
    {
      "name" : "fsh-generated/resources/PractitionerRole-ExamplePractitionerRoleAgregateur2.json",
      "size" : 1393,
      "processes" : [
        {
          "activity" : "loadResources",
          "start" : 37,
          "length" : 4
        },
        {
          "activity" : "generateNarratives",
          "start" : 42,
          "length" : 1
        },
        {
          "activity" : "validate",
          "start" : 64,
          "length" : 24
        },
        {
          "activity" : "generate1",
          "start" : 65,
          "length" : 17
        },
        {
          "activity" : "generate2",
          "start" : 74,
          "length" : 12
        }
      ]
    },
    {
      "name" : "fsh-generated/resources/PractitionerRole-ExamplePractitionerRoleAgregateur3.json",
      "size" : 1394,
      "processes" : [
        {
          "activity" : "loadResources",
          "start" : 37,
          "length" : 5
        },
        {
          "activity" : "checkR4R4B",
          "start" : 41,
          "length" : 1
        },
        {
          "activity" : "generateNarratives",
          "start" : 42,
          "length" : 2
        },
        {
          "activity" : "validate",
          "start" : 64,
          "length" : 17
        },
        {
          "activity" : "generate1",
          "start" : 66,
          "length" : 12
        },
        {
          "activity" : "generate2",
          "start" : 74,
          "length" : 12
        }
      ]
    },
    {
      "name" : "fsh-generated/resources/PractitionerRole-ExamplePractitionerRoleAgregateur4.json",
      "size" : 1480,
      "processes" : [
        {
          "activity" : "loadResources",
          "start" : 37,
          "length" : 4
        },
        {
          "activity" : "load-configure",
          "start" : 41,
          "length" : 1
        },
        {
          "activity" : "generateNarratives",
          "start" : 42,
          "length" : 1
        },
        {
          "activity" : "validate",
          "start" : 64,
          "length" : 19
        },
        {
          "activity" : "generate1",
          "start" : 66,
          "length" : 11
        },
        {
          "activity" : "generate2",
          "start" : 74,
          "length" : 12
        }
      ]
    },
    {
      "name" : "fsh-generated/resources/Schedule-ExampleSchedule.json",
      "size" : 337,
      "processes" : [
        {
          "activity" : "loadResources",
          "start" : 37,
          "length" : 5
        },
        {
          "activity" : "generateNarratives",
          "start" : 42,
          "length" : 1
        },
        {
          "activity" : "validate",
          "start" : 64,
          "length" : 3
        },
        {
          "activity" : "generate1",
          "start" : 66,
          "length" : 9
        },
        {
          "activity" : "generate2",
          "start" : 74,
          "length" : 11
        }
      ]
    },
    {
      "name" : "fsh-generated/resources/Schedule-ExampleSchedule1.json",
      "size" : 340,
      "processes" : [
        {
          "activity" : "loadResources",
          "start" : 37,
          "length" : 4
        },
        {
          "activity" : "validate",
          "start" : 64,
          "length" : 2
        },
        {
          "activity" : "generate1",
          "start" : 66,
          "length" : 9
        },
        {
          "activity" : "generate2",
          "start" : 74,
          "length" : 10
        }
      ]
    },
    {
      "name" : "fsh-generated/resources/Schedule-ExampleSchedule2.json",
      "size" : 340,
      "processes" : [
        {
          "activity" : "loadResources",
          "start" : 37,
          "length" : 4
        },
        {
          "activity" : "generateNarratives",
          "start" : 42,
          "length" : 1
        },
        {
          "activity" : "scanForUsageStats",
          "start" : 60,
          "length" : 1
        },
        {
          "activity" : "validate",
          "start" : 64,
          "length" : 2
        },
        {
          "activity" : "generate1",
          "start" : 66,
          "length" : 10
        },
        {
          "activity" : "generate2",
          "start" : 74,
          "length" : 14
        }
      ]
    },
    {
      "name" : "fsh-generated/resources/Schedule-ExampleSchedule3.json",
      "size" : 340,
      "processes" : [
        {
          "activity" : "loadResources",
          "start" : 37,
          "length" : 5
        },
        {
          "activity" : "load",
          "start" : 38,
          "length" : 1
        },
        {
          "activity" : "validate",
          "start" : 64,
          "length" : 2
        },
        {
          "activity" : "generate1",
          "start" : 66,
          "length" : 9
        },
        {
          "activity" : "generate2",
          "start" : 74,
          "length" : 11
        }
      ]
    },
    {
      "name" : "fsh-generated/resources/Schedule-ExampleScheduleSOS1.json",
      "size" : 274,
      "processes" : [
        {
          "activity" : "loadResources",
          "start" : 37,
          "length" : 4
        },
        {
          "activity" : "generateNarratives",
          "start" : 42,
          "length" : 1
        },
        {
          "activity" : "validate",
          "start" : 64,
          "length" : 2
        },
        {
          "activity" : "generate1",
          "start" : 66,
          "length" : 9
        },
        {
          "activity" : "generate2",
          "start" : 74,
          "length" : 10
        }
      ]
    },
    {
      "name" : "fsh-generated/resources/Schedule-ExampleScheduleSOS2.json",
      "size" : 274,
      "processes" : [
        {
          "activity" : "loadResources",
          "start" : 37,
          "length" : 5
        },
        {
          "activity" : "validate",
          "start" : 64,
          "length" : 1
        },
        {
          "activity" : "generate1",
          "start" : 66,
          "length" : 9
        },
        {
          "activity" : "generate2",
          "start" : 74,
          "length" : 10
        }
      ]
    },
    {
      "name" : "fsh-generated/resources/Schedule-ExampleScheduleSOS3.json",
      "size" : 274,
      "processes" : [
        {
          "activity" : "loadResources",
          "start" : 37,
          "length" : 4
        },
        {
          "activity" : "generateNarratives",
          "start" : 42,
          "length" : 1
        },
        {
          "activity" : "validate",
          "start" : 64,
          "length" : 2
        },
        {
          "activity" : "generate1",
          "start" : 66,
          "length" : 9
        },
        {
          "activity" : "generate2",
          "start" : 74,
          "length" : 10
        }
      ]
    },
    {
      "name" : "fsh-generated/resources/SearchParameter-cptsslot-sp-servicetype.json",
      "size" : 611,
      "processes" : [
        {
          "activity" : "loadResources",
          "start" : 37,
          "length" : 5
        },
        {
          "activity" : "load",
          "start" : 38,
          "length" : 11
        },
        {
          "activity" : "load",
          "start" : 38,
          "length" : 11
        },
        {
          "activity" : "load-configure",
          "start" : 41,
          "length" : 1
        },
        {
          "activity" : "generateNarratives",
          "start" : 42,
          "length" : 11
        },
        {
          "activity" : "validate",
          "start" : 55,
          "length" : 4
        },
        {
          "activity" : "generate1",
          "start" : 66,
          "length" : 12
        },
        {
          "activity" : "generate2",
          "start" : 75,
          "length" : 9
        }
      ]
    },
    {
      "name" : "fsh-generated/resources/SearchParameter-slot-sp-start.json",
      "size" : 598,
      "processes" : [
        {
          "activity" : "loadResources",
          "start" : 37,
          "length" : 4
        },
        {
          "activity" : "load",
          "start" : 38,
          "length" : 7
        },
        {
          "activity" : "load",
          "start" : 38,
          "length" : 6
        },
        {
          "activity" : "generateNarratives",
          "start" : 42,
          "length" : 12
        },
        {
          "activity" : "validate",
          "start" : 55,
          "length" : 2
        },
        {
          "activity" : "generate1",
          "start" : 66,
          "length" : 11
        },
        {
          "activity" : "generate2",
          "start" : 75,
          "length" : 9
        },
        {
          "activity" : "generateValidationPack",
          "start" : 110,
          "length" : 1
        }
      ]
    },
    {
      "name" : "fsh-generated/resources/Slot-ExampleSlotCPTS1.json",
      "size" : 1779,
      "processes" : [
        {
          "activity" : "loadResources",
          "start" : 37,
          "length" : 5
        },
        {
          "activity" : "generateNarratives",
          "start" : 42,
          "length" : 4
        },
        {
          "activity" : "validate",
          "start" : 64,
          "length" : 26
        },
        {
          "activity" : "generate1",
          "start" : 66,
          "length" : 12
        },
        {
          "activity" : "generate2",
          "start" : 75,
          "length" : 15
        }
      ]
    },
    {
      "name" : "fsh-generated/resources/Slot-ExampleSlotCPTS2.json",
      "size" : 2229,
      "processes" : [
        {
          "activity" : "loadResources",
          "start" : 37,
          "length" : 4
        },
        {
          "activity" : "checkR4R4B",
          "start" : 41,
          "length" : 1
        },
        {
          "activity" : "generateNarratives",
          "start" : 42,
          "length" : 3
        },
        {
          "activity" : "validate",
          "start" : 64,
          "length" : 35
        },
        {
          "activity" : "generate1",
          "start" : 66,
          "length" : 13
        },
        {
          "activity" : "generate2",
          "start" : 75,
          "length" : 13
        }
      ]
    },
    {
      "name" : "fsh-generated/resources/Slot-ExampleSlotPSIndiv1.json",
      "size" : 1501,
      "processes" : [
        {
          "activity" : "loadResources",
          "start" : 37,
          "length" : 4
        },
        {
          "activity" : "generateNarratives",
          "start" : 42,
          "length" : 2
        },
        {
          "activity" : "validate",
          "start" : 64,
          "length" : 16
        },
        {
          "activity" : "generate1",
          "start" : 66,
          "length" : 11
        },
        {
          "activity" : "generate2",
          "start" : 75,
          "length" : 11
        }
      ]
    },
    {
      "name" : "fsh-generated/resources/Slot-ExampleSlotPSIndiv2.json",
      "size" : 1096,
      "processes" : [
        {
          "activity" : "loadResources",
          "start" : 37,
          "length" : 8
        },
        {
          "activity" : "generateNarratives",
          "start" : 42,
          "length" : 2
        },
        {
          "activity" : "validate",
          "start" : 64,
          "length" : 11
        },
        {
          "activity" : "generate1",
          "start" : 66,
          "length" : 11
        },
        {
          "activity" : "generate2",
          "start" : 75,
          "length" : 10
        }
      ]
    },
    {
      "name" : "fsh-generated/resources/Slot-ExampleSlotPSIndiv3.json",
      "size" : 1350,
      "processes" : [
        {
          "activity" : "loadResources",
          "start" : 37,
          "length" : 4
        },
        {
          "activity" : "generateNarratives",
          "start" : 42,
          "length" : 2
        },
        {
          "activity" : "validate",
          "start" : 64,
          "length" : 13
        },
        {
          "activity" : "generate1",
          "start" : 66,
          "length" : 11
        },
        {
          "activity" : "generate2",
          "start" : 75,
          "length" : 11
        }
      ]
    },
    {
      "name" : "fsh-generated/resources/Slot-ExampleSlotPSIndiv4.json",
      "size" : 1549,
      "processes" : [
        {
          "activity" : "loadResources",
          "start" : 37,
          "length" : 4
        },
        {
          "activity" : "generateNarratives",
          "start" : 42,
          "length" : 2
        },
        {
          "activity" : "validate",
          "start" : 64,
          "length" : 14
        },
        {
          "activity" : "generate1",
          "start" : 66,
          "length" : 12
        },
        {
          "activity" : "generate2",
          "start" : 75,
          "length" : 11
        }
      ]
    },
    {
      "name" : "fsh-generated/resources/Slot-ExampleSlotSOS1.json",
      "size" : 1219,
      "processes" : [
        {
          "activity" : "loadResources",
          "start" : 37,
          "length" : 5
        },
        {
          "activity" : "generateNarratives",
          "start" : 42,
          "length" : 2
        },
        {
          "activity" : "validate",
          "start" : 64,
          "length" : 12
        },
        {
          "activity" : "generate1",
          "start" : 66,
          "length" : 11
        },
        {
          "activity" : "generate2",
          "start" : 75,
          "length" : 10
        }
      ]
    },
    {
      "name" : "fsh-generated/resources/Slot-ExampleSlotSOS2.json",
      "size" : 927,
      "processes" : [
        {
          "activity" : "loadResources",
          "start" : 37,
          "length" : 4
        },
        {
          "activity" : "load-configure",
          "start" : 41,
          "length" : 1
        },
        {
          "activity" : "checkR4R4B",
          "start" : 41,
          "length" : 1
        },
        {
          "activity" : "generateNarratives",
          "start" : 42,
          "length" : 2
        },
        {
          "activity" : "validate",
          "start" : 64,
          "length" : 10
        },
        {
          "activity" : "generate1",
          "start" : 66,
          "length" : 10
        },
        {
          "activity" : "generate2",
          "start" : 75,
          "length" : 10
        }
      ]
    },
    {
      "name" : "fsh-generated/resources/Slot-ExampleSlotSOS3.json",
      "size" : 926,
      "processes" : [
        {
          "activity" : "loadResources",
          "start" : 37,
          "length" : 5
        },
        {
          "activity" : "generateNarratives",
          "start" : 42,
          "length" : 1
        },
        {
          "activity" : "validate",
          "start" : 64,
          "length" : 10
        },
        {
          "activity" : "generate1",
          "start" : 66,
          "length" : 10
        },
        {
          "activity" : "generate2",
          "start" : 75,
          "length" : 10
        }
      ]
    },
    {
      "name" : "fsh-generated/resources/Slot-ExampleSlotSOS4.json",
      "size" : 927,
      "processes" : [
        {
          "activity" : "loadResources",
          "start" : 37,
          "length" : 4
        },
        {
          "activity" : "generateNarratives",
          "start" : 42,
          "length" : 2
        },
        {
          "activity" : "validate",
          "start" : 64,
          "length" : 9
        },
        {
          "activity" : "generate1",
          "start" : 66,
          "length" : 11
        },
        {
          "activity" : "generate2",
          "start" : 75,
          "length" : 10
        }
      ]
    },
    {
      "name" : "fsh-generated/resources/StructureDefinition-BundleAgregateur.json",
      "size" : 3082,
      "processes" : [
        {
          "activity" : "loadResources",
          "start" : 37,
          "length" : 5
        },
        {
          "activity" : "load",
          "start" : 38,
          "length" : 15
        },
        {
          "activity" : "generateSnapshots",
          "start" : 38,
          "length" : 523
        },
        {
          "activity" : "generateNarratives",
          "start" : 42,
          "length" : 113
        },
        {
          "activity" : "validate",
          "start" : 44,
          "length" : 1231
        },
        {
          "activity" : "checkConformanceResources",
          "start" : 60,
          "length" : 1
        },
        {
          "activity" : "scanForUsageStats",
          "start" : 60,
          "length" : 1
        },
        {
          "activity" : "generate1",
          "start" : 66,
          "length" : 337
        },
        {
          "activity" : "generate2",
          "start" : 75,
          "length" : 2375
        },
        {
          "activity" : "generate2",
          "start" : 86,
          "length" : 1351
        },
        {
          "activity" : "generateValidationPack",
          "start" : 110,
          "length" : 19
        },
        {
          "activity" : "scanExamplesForR5",
          "start" : 138,
          "length" : 2
        }
      ]
    },
    {
      "name" : "fsh-generated/resources/StructureDefinition-FrAppointmentSAS.json",
      "size" : 5246,
      "processes" : [
        {
          "activity" : "loadResources",
          "start" : 37,
          "length" : 5
        },
        {
          "activity" : "load",
          "start" : 38,
          "length" : 14
        },
        {
          "activity" : "generateSnapshots",
          "start" : 38,
          "length" : 160
        },
        {
          "activity" : "generateNarratives",
          "start" : 42,
          "length" : 80
        },
        {
          "activity" : "validate",
          "start" : 45,
          "length" : 764
        },
        {
          "activity" : "scanForUsageStats",
          "start" : 60,
          "length" : 1
        },
        {
          "activity" : "generate1",
          "start" : 66,
          "length" : 367
        },
        {
          "activity" : "generate2",
          "start" : 77,
          "length" : 801
        },
        {
          "activity" : "generate2",
          "start" : 87,
          "length" : 482
        },
        {
          "activity" : "makeDependencies",
          "start" : 94,
          "length" : 1
        },
        {
          "activity" : "generateValidationPack",
          "start" : 110,
          "length" : 16
        },
        {
          "activity" : "scanExamplesForR5",
          "start" : 138,
          "length" : 1
        }
      ]
    },
    {
      "name" : "fsh-generated/resources/StructureDefinition-FrLocationAgregateur.json",
      "size" : 1491,
      "processes" : [
        {
          "activity" : "loadResources",
          "start" : 37,
          "length" : 5
        },
        {
          "activity" : "load",
          "start" : 38,
          "length" : 10
        },
        {
          "activity" : "generateSnapshots",
          "start" : 39,
          "length" : 136
        },
        {
          "activity" : "generateNarratives",
          "start" : 42,
          "length" : 36
        },
        {
          "activity" : "validate",
          "start" : 46,
          "length" : 434
        },
        {
          "activity" : "scanForUsageStats",
          "start" : 60,
          "length" : 1
        },
        {
          "activity" : "generate1",
          "start" : 66,
          "length" : 178
        },
        {
          "activity" : "generate2",
          "start" : 78,
          "length" : 310
        },
        {
          "activity" : "generate2",
          "start" : 87,
          "length" : 247
        },
        {
          "activity" : "generateValidationPack",
          "start" : 110,
          "length" : 10
        },
        {
          "activity" : "scanExamplesForR5",
          "start" : 138,
          "length" : 1
        }
      ]
    },
    {
      "name" : "fsh-generated/resources/StructureDefinition-FrPractitionerAgregateur.json",
      "size" : 1817,
      "processes" : [
        {
          "activity" : "loadResources",
          "start" : 37,
          "length" : 5
        },
        {
          "activity" : "load",
          "start" : 38,
          "length" : 8
        },
        {
          "activity" : "generateSnapshots",
          "start" : 39,
          "length" : 157
        },
        {
          "activity" : "load-configure",
          "start" : 41,
          "length" : 1
        },
        {
          "activity" : "generateNarratives",
          "start" : 42,
          "length" : 75
        },
        {
          "activity" : "validate",
          "start" : 47,
          "length" : 1298
        },
        {
          "activity" : "scanForUsageStats",
          "start" : 60,
          "length" : 2
        },
        {
          "activity" : "generate1",
          "start" : 67,
          "length" : 389
        },
        {
          "activity" : "generate2",
          "start" : 78,
          "length" : 609
        },
        {
          "activity" : "generate2",
          "start" : 88,
          "length" : 490
        },
        {
          "activity" : "generateValidationPack",
          "start" : 110,
          "length" : 20
        },
        {
          "activity" : "scanExamplesForR5",
          "start" : 138,
          "length" : 2
        }
      ]
    },
    {
      "name" : "fsh-generated/resources/StructureDefinition-FrPractitionerRegul.json",
      "size" : 3078,
      "processes" : [
        {
          "activity" : "loadResources",
          "start" : 37,
          "length" : 5
        },
        {
          "activity" : "load",
          "start" : 38,
          "length" : 6
        },
        {
          "activity" : "generateSnapshots",
          "start" : 39,
          "length" : 172
        },
        {
          "activity" : "generateNarratives",
          "start" : 42,
          "length" : 95
        },
        {
          "activity" : "validate",
          "start" : 48,
          "length" : 1180
        },
        {
          "activity" : "checkConformanceResources",
          "start" : 60,
          "length" : 1
        },
        {
          "activity" : "scanForUsageStats",
          "start" : 60,
          "length" : 2
        },
        {
          "activity" : "generate1",
          "start" : 67,
          "length" : 512
        },
        {
          "activity" : "generate2",
          "start" : 79,
          "length" : 1169
        },
        {
          "activity" : "generate2",
          "start" : 88,
          "length" : 499
        },
        {
          "activity" : "generateValidationPack",
          "start" : 110,
          "length" : 30
        },
        {
          "activity" : "scanProfilesForR5",
          "start" : 138,
          "length" : 1
        },
        {
          "activity" : "scanExamplesForR5",
          "start" : 138,
          "length" : 3
        }
      ]
    },
    {
      "name" : "fsh-generated/resources/StructureDefinition-FrPractitionerRoleExerciceAgregateur.json",
      "size" : 2533,
      "processes" : [
        {
          "activity" : "loadResources",
          "start" : 37,
          "length" : 4
        },
        {
          "activity" : "load",
          "start" : 38,
          "length" : 6
        },
        {
          "activity" : "generateSnapshots",
          "start" : 39,
          "length" : 36
        },
        {
          "activity" : "generateNarratives",
          "start" : 42,
          "length" : 37
        },
        {
          "activity" : "validate",
          "start" : 49,
          "length" : 255
        },
        {
          "activity" : "scanForUsageStats",
          "start" : 60,
          "length" : 1
        },
        {
          "activity" : "generate1",
          "start" : 68,
          "length" : 151
        },
        {
          "activity" : "generate2",
          "start" : 80,
          "length" : 440
        },
        {
          "activity" : "generate2",
          "start" : 89,
          "length" : 159
        },
        {
          "activity" : "generateValidationPack",
          "start" : 110,
          "length" : 9
        },
        {
          "activity" : "scanExamplesForR5",
          "start" : 138,
          "length" : 1
        }
      ]
    },
    {
      "name" : "fsh-generated/resources/StructureDefinition-FrScheduleAgregateur.json",
      "size" : 1469,
      "processes" : [
        {
          "activity" : "loadResources",
          "start" : 37,
          "length" : 4
        },
        {
          "activity" : "load",
          "start" : 38,
          "length" : 5
        },
        {
          "activity" : "generateSnapshots",
          "start" : 39,
          "length" : 28
        },
        {
          "activity" : "generateNarratives",
          "start" : 42,
          "length" : 18
        },
        {
          "activity" : "validate",
          "start" : 49,
          "length" : 116
        },
        {
          "activity" : "generate1",
          "start" : 68,
          "length" : 72
        },
        {
          "activity" : "generate2",
          "start" : 80,
          "length" : 224
        },
        {
          "activity" : "generate2",
          "start" : 89,
          "length" : 72
        },
        {
          "activity" : "generateValidationPack",
          "start" : 110,
          "length" : 5
        }
      ]
    },
    {
      "name" : "fsh-generated/resources/StructureDefinition-FrSlotAgregateur.json",
      "size" : 4381,
      "processes" : [
        {
          "activity" : "loadResources",
          "start" : 37,
          "length" : 5
        },
        {
          "activity" : "load",
          "start" : 38,
          "length" : 8
        },
        {
          "activity" : "generateSnapshots",
          "start" : 39,
          "length" : 32
        },
        {
          "activity" : "generateNarratives",
          "start" : 42,
          "length" : 34
        },
        {
          "activity" : "validate",
          "start" : 49,
          "length" : 213
        },
        {
          "activity" : "generate1",
          "start" : 68,
          "length" : 134
        },
        {
          "activity" : "generate2",
          "start" : 81,
          "length" : 320
        },
        {
          "activity" : "generate2",
          "start" : 89,
          "length" : 99
        },
        {
          "activity" : "generateValidationPack",
          "start" : 110,
          "length" : 8
        },
        {
          "activity" : "scanExamplesForR5",
          "start" : 138,
          "length" : 1
        }
      ]
    },
    {
      "name" : "fsh-generated/resources/StructureDefinition-sas-categorie-orientation.json",
      "size" : 1500,
      "processes" : [
        {
          "activity" : "loadResources",
          "start" : 37,
          "length" : 5
        },
        {
          "activity" : "load",
          "start" : 38,
          "length" : 5
        },
        {
          "activity" : "generateSnapshots",
          "start" : 39,
          "length" : 30
        },
        {
          "activity" : "generateNarratives",
          "start" : 42,
          "length" : 13
        },
        {
          "activity" : "validate",
          "start" : 50,
          "length" : 2425
        },
        {
          "activity" : "generate1",
          "start" : 68,
          "length" : 36
        },
        {
          "activity" : "generate2",
          "start" : 81,
          "length" : 96
        },
        {
          "activity" : "generate2",
          "start" : 89,
          "length" : 27
        },
        {
          "activity" : "generateValidationPack",
          "start" : 110,
          "length" : 1
        }
      ]
    },
    {
      "name" : "fsh-generated/resources/StructureDefinition-sas-cpts-bundle-aggregator.json",
      "size" : 5247,
      "processes" : [
        {
          "activity" : "loadResources",
          "start" : 37,
          "length" : 5
        },
        {
          "activity" : "load",
          "start" : 38,
          "length" : 6
        },
        {
          "activity" : "generateSnapshots",
          "start" : 39,
          "length" : 264
        },
        {
          "activity" : "checkR4R4B",
          "start" : 41,
          "length" : 1
        },
        {
          "activity" : "generateNarratives",
          "start" : 42,
          "length" : 81
        },
        {
          "activity" : "validate",
          "start" : 52,
          "length" : 699
        },
        {
          "activity" : "scanForUsageStats",
          "start" : 60,
          "length" : 2
        },
        {
          "activity" : "generate1",
          "start" : 68,
          "length" : 448
        },
        {
          "activity" : "generate2",
          "start" : 81,
          "length" : 998
        },
        {
          "activity" : "generate2",
          "start" : 89,
          "length" : 335
        },
        {
          "activity" : "generateExampleZip",
          "start" : 109,
          "length" : 1
        },
        {
          "activity" : "generateValidationPack",
          "start" : 110,
          "length" : 25
        },
        {
          "activity" : "scanExamplesForR5",
          "start" : 138,
          "length" : 2
        }
      ]
    },
    {
      "name" : "fsh-generated/resources/StructureDefinition-sas-cpts-healthcareservice-aggregator.json",
      "size" : 1216,
      "processes" : [
        {
          "activity" : "loadResources",
          "start" : 37,
          "length" : 4
        },
        {
          "activity" : "load",
          "start" : 38,
          "length" : 5
        },
        {
          "activity" : "generateSnapshots",
          "start" : 39,
          "length" : 38
        },
        {
          "activity" : "generateNarratives",
          "start" : 42,
          "length" : 25
        },
        {
          "activity" : "validate",
          "start" : 53,
          "length" : 221
        },
        {
          "activity" : "checkConformanceResources",
          "start" : 60,
          "length" : 1
        },
        {
          "activity" : "scanForUsageStats",
          "start" : 60,
          "length" : 1
        },
        {
          "activity" : "generate1",
          "start" : 68,
          "length" : 124
        },
        {
          "activity" : "generate2",
          "start" : 82,
          "length" : 229
        },
        {
          "activity" : "generate2",
          "start" : 89,
          "length" : 77
        },
        {
          "activity" : "generateValidationPack",
          "start" : 110,
          "length" : 7
        },
        {
          "activity" : "scanExamplesForR5",
          "start" : 138,
          "length" : 1
        }
      ]
    },
    {
      "name" : "fsh-generated/resources/StructureDefinition-sas-cpts-organization-aggregator.json",
      "size" : 1936,
      "processes" : [
        {
          "activity" : "loadResources",
          "start" : 37,
          "length" : 5
        },
        {
          "activity" : "load",
          "start" : 38,
          "length" : 6
        },
        {
          "activity" : "generateSnapshots",
          "start" : 39,
          "length" : 34
        },
        {
          "activity" : "generateNarratives",
          "start" : 42,
          "length" : 37
        },
        {
          "activity" : "validate",
          "start" : 53,
          "length" : 422
        },
        {
          "activity" : "scanForUsageStats",
          "start" : 60,
          "length" : 1
        },
        {
          "activity" : "generate1",
          "start" : 68,
          "length" : 190
        },
        {
          "activity" : "generate2",
          "start" : 82,
          "length" : 283
        },
        {
          "activity" : "generate2",
          "start" : 89,
          "length" : 144
        },
        {
          "activity" : "generateValidationPack",
          "start" : 110,
          "length" : 12
        },
        {
          "activity" : "scanExamplesForR5",
          "start" : 138,
          "length" : 1
        }
      ]
    },
    {
      "name" : "fsh-generated/resources/StructureDefinition-sas-cpts-slot-aggregator.json",
      "size" : 4598,
      "processes" : [
        {
          "activity" : "loadResources",
          "start" : 37,
          "length" : 5
        },
        {
          "activity" : "load",
          "start" : 38,
          "length" : 12
        },
        {
          "activity" : "generateSnapshots",
          "start" : 40,
          "length" : 17
        },
        {
          "activity" : "load-configure",
          "start" : 41,
          "length" : 1
        },
        {
          "activity" : "generateNarratives",
          "start" : 42,
          "length" : 40
        },
        {
          "activity" : "validate",
          "start" : 53,
          "length" : 233
        },
        {
          "activity" : "generate1",
          "start" : 69,
          "length" : 178
        },
        {
          "activity" : "generate2",
          "start" : 82,
          "length" : 215
        },
        {
          "activity" : "generate2",
          "start" : 90,
          "length" : 93
        },
        {
          "activity" : "generateValidationPack",
          "start" : 110,
          "length" : 10
        },
        {
          "activity" : "scanExamplesForR5",
          "start" : 138,
          "length" : 1
        }
      ]
    },
    {
      "name" : "fsh-generated/resources/StructureDefinition-sas-cpts-slot-servicetype-aggregator.json",
      "size" : 1669,
      "processes" : [
        {
          "activity" : "loadResources",
          "start" : 37,
          "length" : 4
        },
        {
          "activity" : "load",
          "start" : 38,
          "length" : 11
        },
        {
          "activity" : "generateSnapshots",
          "start" : 40,
          "length" : 5
        },
        {
          "activity" : "generateNarratives",
          "start" : 43,
          "length" : 12
        },
        {
          "activity" : "validate",
          "start" : 54,
          "length" : 25
        },
        {
          "activity" : "generate1",
          "start" : 69,
          "length" : 30
        },
        {
          "activity" : "generate2",
          "start" : 83,
          "length" : 64
        },
        {
          "activity" : "generate2",
          "start" : 90,
          "length" : 17
        },
        {
          "activity" : "generateValidationPack",
          "start" : 110,
          "length" : 1
        }
      ]
    },
    {
      "name" : "fsh-generated/resources/StructureDefinition-sas-sos-appointment.json",
      "size" : 4193,
      "processes" : [
        {
          "activity" : "loadResources",
          "start" : 37,
          "length" : 8
        },
        {
          "activity" : "load",
          "start" : 38,
          "length" : 9
        },
        {
          "activity" : "generateSnapshots",
          "start" : 40,
          "length" : 57
        },
        {
          "activity" : "generateNarratives",
          "start" : 43,
          "length" : 37
        },
        {
          "activity" : "validate",
          "start" : 54,
          "length" : 268
        },
        {
          "activity" : "scanForUsageStats",
          "start" : 60,
          "length" : 1
        },
        {
          "activity" : "generate1",
          "start" : 69,
          "length" : 213
        },
        {
          "activity" : "generate2",
          "start" : 83,
          "length" : 371
        },
        {
          "activity" : "generate2",
          "start" : 90,
          "length" : 110
        },
        {
          "activity" : "generateValidationPack",
          "start" : 110,
          "length" : 13
        },
        {
          "activity" : "scanProfilesForR5",
          "start" : 138,
          "length" : 1
        }
      ]
    },
    {
      "name" : "fsh-generated/resources/StructureDefinition-sas-sos-bundle-aggregator.json",
      "size" : 3965,
      "processes" : [
        {
          "activity" : "loadResources",
          "start" : 37,
          "length" : 4
        },
        {
          "activity" : "load",
          "start" : 38,
          "length" : 9
        },
        {
          "activity" : "generateSnapshots",
          "start" : 40,
          "length" : 229
        },
        {
          "activity" : "generateNarratives",
          "start" : 43,
          "length" : 52
        },
        {
          "activity" : "validate",
          "start" : 54,
          "length" : 445
        },
        {
          "activity" : "scanForUsageStats",
          "start" : 60,
          "length" : 2
        },
        {
          "activity" : "generate1",
          "start" : 69,
          "length" : 325
        },
        {
          "activity" : "generate2",
          "start" : 83,
          "length" : 783
        },
        {
          "activity" : "generate2",
          "start" : 90,
          "length" : 201
        },
        {
          "activity" : "generateValidationPack",
          "start" : 110,
          "length" : 19
        },
        {
          "activity" : "scanExamplesForR5",
          "start" : 138,
          "length" : 2
        }
      ]
    },
    {
      "name" : "fsh-generated/resources/StructureDefinition-sas-sos-location-aggregator.json",
      "size" : 2114,
      "processes" : [
        {
          "activity" : "loadResources",
          "start" : 37,
          "length" : 5
        },
        {
          "activity" : "load",
          "start" : 38,
          "length" : 6
        },
        {
          "activity" : "generateSnapshots",
          "start" : 40,
          "length" : 15
        },
        {
          "activity" : "generateNarratives",
          "start" : 43,
          "length" : 87
        },
        {
          "activity" : "validate",
          "start" : 54,
          "length" : 223
        },
        {
          "activity" : "generate1",
          "start" : 69,
          "length" : 171
        },
        {
          "activity" : "generate2",
          "start" : 84,
          "length" : 370
        },
        {
          "activity" : "generate2",
          "start" : 90,
          "length" : 91
        },
        {
          "activity" : "generateValidationPack",
          "start" : 110,
          "length" : 15
        }
      ]
    },
    {
      "name" : "fsh-generated/resources/StructureDefinition-sas-sos-organization-aggregator.json",
      "size" : 1743,
      "processes" : [
        {
          "activity" : "loadResources",
          "start" : 37,
          "length" : 4
        },
        {
          "activity" : "load",
          "start" : 38,
          "length" : 5
        },
        {
          "activity" : "generateSnapshots",
          "start" : 40,
          "length" : 16
        },
        {
          "activity" : "generateNarratives",
          "start" : 43,
          "length" : 21
        },
        {
          "activity" : "validate",
          "start" : 55,
          "length" : 375
        },
        {
          "activity" : "checkConformanceResources",
          "start" : 60,
          "length" : 1
        },
        {
          "activity" : "scanForUsageStats",
          "start" : 60,
          "length" : 30
        },
        {
          "activity" : "generate1",
          "start" : 70,
          "length" : 186
        },
        {
          "activity" : "generate2",
          "start" : 84,
          "length" : 429
        },
        {
          "activity" : "generate2",
          "start" : 90,
          "length" : 92
        },
        {
          "activity" : "generateValidationPack",
          "start" : 110,
          "length" : 11
        },
        {
          "activity" : "scanExamplesForR5",
          "start" : 138,
          "length" : 1
        }
      ]
    },
    {
      "name" : "fsh-generated/resources/StructureDefinition-sas-sos-schedule-aggregator.json",
      "size" : 1065,
      "processes" : [
        {
          "activity" : "loadResources",
          "start" : 37,
          "length" : 5
        },
        {
          "activity" : "load",
          "start" : 38,
          "length" : 5
        },
        {
          "activity" : "generateSnapshots",
          "start" : 40,
          "length" : 9
        },
        {
          "activity" : "generateNarratives",
          "start" : 43,
          "length" : 11
        },
        {
          "activity" : "validate",
          "start" : 55,
          "length" : 109
        },
        {
          "activity" : "generate1",
          "start" : 70,
          "length" : 85
        },
        {
          "activity" : "generate2",
          "start" : 85,
          "length" : 203
        },
        {
          "activity" : "generate2",
          "start" : 90,
          "length" : 49
        },
        {
          "activity" : "generateValidationPack",
          "start" : 110,
          "length" : 5
        }
      ]
    },
    {
      "name" : "fsh-generated/resources/StructureDefinition-sas-sos-slot-aggregator.json",
      "size" : 1926,
      "processes" : [
        {
          "activity" : "loadResources",
          "start" : 37,
          "length" : 4
        },
        {
          "activity" : "load",
          "start" : 38,
          "length" : 5
        },
        {
          "activity" : "generateSnapshots",
          "start" : 40,
          "length" : 11
        },
        {
          "activity" : "scan",
          "start" : 41,
          "length" : 1
        },
        {
          "activity" : "generateNarratives",
          "start" : 43,
          "length" : 16
        },
        {
          "activity" : "validate",
          "start" : 55,
          "length" : 133
        },
        {
          "activity" : "scanForUsageStats",
          "start" : 60,
          "length" : 1
        },
        {
          "activity" : "generate1",
          "start" : 70,
          "length" : 109
        },
        {
          "activity" : "generate2",
          "start" : 85,
          "length" : 221
        },
        {
          "activity" : "generate2",
          "start" : 90,
          "length" : 58
        },
        {
          "activity" : "generateValidationPack",
          "start" : 110,
          "length" : 6
        },
        {
          "activity" : "scanExamplesForR5",
          "start" : 138,
          "length" : 1
        }
      ]
    },
    {
      "name" : "fsh-generated/resources/ValueSet-categorie-orientation-sas-valueset.json",
      "size" : 1066,
      "processes" : [
        {
          "activity" : "loadResources",
          "start" : 37,
          "length" : 5
        },
        {
          "activity" : "load",
          "start" : 38,
          "length" : 6
        },
        {
          "activity" : "load",
          "start" : 38,
          "length" : 1
        },
        {
          "activity" : "generateNarratives",
          "start" : 43,
          "length" : 61
        },
        {
          "activity" : "validate",
          "start" : 44,
          "length" : 68
        },
        {
          "activity" : "generate1",
          "start" : 70,
          "length" : 14
        },
        {
          "activity" : "generate2",
          "start" : 85,
          "length" : 83
        },
        {
          "activity" : "generateValidationPack",
          "start" : 110,
          "length" : 1
        }
      ]
    },
    {
      "name" : "fsh-generated/resources/ValueSet-sas-cpts-valueset-typecreneau.json",
      "size" : 1041,
      "processes" : [
        {
          "activity" : "loadResources",
          "start" : 37,
          "length" : 4
        },
        {
          "activity" : "load",
          "start" : 38,
          "length" : 6
        },
        {
          "activity" : "generateNarratives",
          "start" : 43,
          "length" : 7
        },
        {
          "activity" : "validate",
          "start" : 44,
          "length" : 14
        },
        {
          "activity" : "generate1",
          "start" : 70,
          "length" : 14
        },
        {
          "activity" : "generate2",
          "start" : 85,
          "length" : 54
        },
        {
          "activity" : "generateValidationPack",
          "start" : 110,
          "length" : 1
        }
      ]
    },
    {
      "name" : "fsh-generated/resources/ValueSet-sas-sos-valueset-participant-status.json",
      "size" : 779,
      "processes" : [
        {
          "activity" : "loadResources",
          "start" : 38,
          "length" : 4
        },
        {
          "activity" : "load",
          "start" : 38,
          "length" : 5
        },
        {
          "activity" : "load-configure",
          "start" : 41,
          "length" : 1
        },
        {
          "activity" : "generateNarratives",
          "start" : 43,
          "length" : 5
        },
        {
          "activity" : "validate",
          "start" : 44,
          "length" : 12
        },
        {
          "activity" : "generate1",
          "start" : 70,
          "length" : 10
        },
        {
          "activity" : "generate2",
          "start" : 85,
          "length" : 49
        }
      ]
    },
    {
      "name" : "fsh-generated/resources/ValueSet-sas-sos-valueset-typecreneau.json",
      "size" : 795,
      "processes" : [
        {
          "activity" : "loadResources",
          "start" : 38,
          "length" : 5
        },
        {
          "activity" : "load",
          "start" : 38,
          "length" : 6
        },
        {
          "activity" : "checkR4R4B",
          "start" : 41,
          "length" : 1
        },
        {
          "activity" : "generateNarratives",
          "start" : 43,
          "length" : 6
        },
        {
          "activity" : "validate",
          "start" : 44,
          "length" : 10
        },
        {
          "activity" : "generate1",
          "start" : 70,
          "length" : 11
        },
        {
          "activity" : "generate2",
          "start" : 85,
          "length" : 47
        }
      ]
    },
    {
      "name" : "fsh-generated/resources/ValueSet-sas-valueset-appointmentparticipanttype.json",
      "size" : 706,
      "processes" : [
        {
          "activity" : "loadResources",
          "start" : 38,
          "length" : 4
        },
        {
          "activity" : "load",
          "start" : 38,
          "length" : 5
        },
        {
          "activity" : "generateNarratives",
          "start" : 43,
          "length" : 10
        },
        {
          "activity" : "validate",
          "start" : 44,
          "length" : 17
        },
        {
          "activity" : "generate1",
          "start" : 70,
          "length" : 10
        },
        {
          "activity" : "generate2",
          "start" : 85,
          "length" : 44
        }
      ]
    },
    {
      "name" : "fsh-generated/resources/ValueSet-sas-valueset-appointmentreason.json",
      "size" : 732,
      "processes" : [
        {
          "activity" : "loadResources",
          "start" : 38,
          "length" : 4
        },
        {
          "activity" : "load",
          "start" : 38,
          "length" : 5
        },
        {
          "activity" : "generateNarratives",
          "start" : 43,
          "length" : 6
        },
        {
          "activity" : "validate",
          "start" : 44,
          "length" : 12
        },
        {
          "activity" : "generate1",
          "start" : 70,
          "length" : 11
        },
        {
          "activity" : "generate2",
          "start" : 85,
          "length" : 44
        },
        {
          "activity" : "generateValidationPack",
          "start" : 110,
          "length" : 1
        }
      ]
    },
    {
      "name" : "fsh-generated/resources/ValueSet-sas-valueset-categorieetablissement.json",
      "size" : 705,
      "processes" : [
        {
          "activity" : "loadResources",
          "start" : 38,
          "length" : 4
        },
        {
          "activity" : "load",
          "start" : 38,
          "length" : 5
        },
        {
          "activity" : "generateNarratives",
          "start" : 43,
          "length" : 5
        },
        {
          "activity" : "validate",
          "start" : 44,
          "length" : 10
        },
        {
          "activity" : "generate1",
          "start" : 70,
          "length" : 19
        },
        {
          "activity" : "generate2",
          "start" : 85,
          "length" : 46
        }
      ]
    },
    {
      "name" : "fsh-generated/resources/ValueSet-sas-valueset-typeconsultation.json",
      "size" : 786,
      "processes" : [
        {
          "activity" : "loadResources",
          "start" : 38,
          "length" : 5
        },
        {
          "activity" : "load",
          "start" : 38,
          "length" : 5
        },
        {
          "activity" : "generateNarratives",
          "start" : 43,
          "length" : 5
        },
        {
          "activity" : "validate",
          "start" : 44,
          "length" : 113
        },
        {
          "activity" : "generate1",
          "start" : 70,
          "length" : 13
        },
        {
          "activity" : "generate2",
          "start" : 86,
          "length" : 44
        }
      ]
    },
    {
      "name" : "fsh-generated/resources/ValueSet-sas-valueset-typeidentifiant.json",
      "size" : 710,
      "processes" : [
        {
          "activity" : "loadResources",
          "start" : 38,
          "length" : 4
        },
        {
          "activity" : "load",
          "start" : 38,
          "length" : 5
        },
        {
          "activity" : "generateNarratives",
          "start" : 43,
          "length" : 9
        },
        {
          "activity" : "validate",
          "start" : 44,
          "length" : 10
        },
        {
          "activity" : "generate1",
          "start" : 70,
          "length" : 10
        },
        {
          "activity" : "generate2",
          "start" : 86,
          "length" : 41
        },
        {
          "activity" : "generateValidationPack",
          "start" : 110,
          "length" : 1
        }
      ]
    },
    {
      "name" : "/fsh-generated/includes/fsh-link-references.md",
      "size" : 5645
    },
    {
      "name" : "/fsh-generated/includes/menu.xml",
      "size" : 3944
    },
    {
      "name" : "/input/data/features.yml",
      "size" : 178
    },
    {
      "name" : "/input/pagecontent/specifications_techniques-cpts-gestion_rdv.md",
      "size" : 11100
    },
    {
      "name" : "/input/pagecontent/specifications_techniques.md",
      "size" : 0
    },
    {
      "name" : "/input/pagecontent/specifications_techniques-ps-gestion_rdv.md",
      "size" : 11100
    },
    {
      "name" : "/input/pagecontent/specifications_techniques-tous-gestion_regulateur.md",
      "size" : 8420,
      "processes" : [
        {
          "activity" : "generate2",
          "start" : 86,
          "length" : 1
        }
      ]
    },
    {
      "name" : "/input/pagecontent/specifications_techniques-sos-gestion_regulateur.md",
      "size" : 8420
    },
    {
      "name" : "/input/pagecontent/specifications_techniques.txt",
      "size" : 587,
      "processes" : [
        {
          "activity" : "generate2",
          "start" : 86,
          "length" : 33
        }
      ]
    },
    {
      "name" : "/input/pagecontent/specifications_techniques-tous-gestion_rdv.md",
      "size" : 11100
    },
    {
      "name" : "/input/pagecontent/specifications_techniques-cpts-gestion_regulateur.md",
      "size" : 8420,
      "processes" : [
        {
          "activity" : "generate2",
          "start" : 86,
          "length" : 1
        }
      ]
    },
    {
      "name" : "/input/pagecontent/specifications_techniques-transmission-info-RDV-LRM.md",
      "size" : 32481
    },
    {
      "name" : "/input/pagecontent/specifications_fonctionnelles.md",
      "size" : 22986,
      "processes" : [
        {
          "activity" : "generate2",
          "start" : 86,
          "length" : 1
        }
      ]
    },
    {
      "name" : "/input/pagecontent/securite.md",
      "size" : 2262
    },
    {
      "name" : "/input/pagecontent/ressources_casusage.md",
      "size" : 1957,
      "processes" : [
        {
          "activity" : "generate2",
          "start" : 86,
          "length" : 17
        }
      ]
    },
    {
      "name" : "/input/pagecontent/faq.md",
      "size" : 25185
    },
    {
      "name" : "/input/pagecontent/specifications_techniques-sos-gestion_rdv.md",
      "size" : 11100,
      "processes" : [
        {
          "activity" : "generate2",
          "start" : 86,
          "length" : 1
        }
      ]
    },
    {
      "name" : "/input/pagecontent/annexes.md",
      "size" : 2431
    },
    {
      "name" : "/input/pagecontent/specifications_techniques-ps-recherche_creneaux.md",
      "size" : 14220,
      "processes" : [
        {
          "activity" : "validate",
          "start" : 44,
          "length" : 1
        }
      ]
    },
    {
      "name" : "/input/pagecontent/specifications_techniques-ps-gestion_regulateur.md",
      "size" : 8420
    },
    {
      "name" : "/input/pagecontent/specifications_techniques-sos-recherche_creneaux.md",
      "size" : 17153,
      "processes" : [
        {
          "activity" : "validate",
          "start" : 57,
          "length" : 1
        },
        {
          "activity" : "generate2",
          "start" : 86,
          "length" : 1
        }
      ]
    },
    {
      "name" : "/input/pagecontent/acronymes.md",
      "size" : 1504
    },
    {
      "name" : "/input/pagecontent/downloads.md",
      "size" : 968
    },
    {
      "name" : "/input/pagecontent/specifications_techniques-cpts-recherche_creneaux.md",
      "size" : 15707
    },
    {
      "name" : "/input/pagecontent/index.md",
      "size" : 5259
    },
    {
      "name" : "/input/pagecontent/autres_ressources.md",
      "size" : 0
    },
    {
      "name" : "/template/config",
      "size" : 0
    },
    {
      "name" : "/template/config/_config.yml",
      "size" : 140
    },
    {
      "name" : "/input/images",
      "size" : 0
    },
    {
      "name" : "/input/images/validateur_creneaux-SOS_1.png",
      "size" : 41943
    },
    {
      "name" : "/input/images/validateur_rendez_vous_1.png",
      "size" : 38959
    },
    {
      "name" : "/input/images/recherche_creneaux_2.png",
      "size" : 135856
    },
    {
      "name" : "/input/images/recherche_creneaux_1.png",
      "size" : 121139
    },
    {
      "name" : "/input/images/anImage.png",
      "size" : 36288
    },
    {
      "name" : "/input/images/validateur_creneaux-PS_1.png",
      "size" : 235493,
      "processes" : [
        {
          "activity" : "generate2",
          "start" : 86,
          "length" : 1
        }
      ]
    },
    {
      "name" : "/input/images/schema_mtls.jpg",
      "size" : 25899
    },
    {
      "name" : "/input/images/redescente_rdv_lrm.png",
      "size" : 110368
    },
    {
      "name" : "/input/images/SchemaGlobalRedescenteLRM.png",
      "size" : 69754
    },
    {
      "name" : "/input/images/validateur_rendez_vous_2.png",
      "size" : 40120
    },
    {
      "name" : "/input/images/mecanisme_transmission_regulateurs.png",
      "size" : 62878
    },
    {
      "name" : "/input/images/sas_logo.png",
      "size" : 113157
    },
    {
      "name" : "/input/images/validateur_creneaux-CPTS_2.png",
      "size" : 76542,
      "processes" : [
        {
          "activity" : "generate2",
          "start" : 86,
          "length" : 1
        }
      ]
    },
    {
      "name" : "/input/images/validateur_creneaux-CPTS_1.png",
      "size" : 341806
    },
    {
      "name" : "/input/images/validateur_creneaux-PS_2.png",
      "size" : 76542
    },
    {
      "name" : "/input/images/schema_cas_usage.png",
      "size" : 118501
    },
    {
      "name" : "/input/images/logo_sas.png",
      "size" : 39358
    },
    {
      "name" : "/input/images/creation_rendez_vous_1.png",
      "size" : 24681
    },
    {
      "name" : "/temp/pages/_includes/artifacts.xml",
      "size" : 37551,
      "processes" : [
        {
          "activity" : "generate2",
          "start" : 86,
          "length" : 1
        }
      ]
    }
  ]
}
